{
  "kanda": "Kishkindha Kanda",
  "kanda_slug": "kishkindha-kanda",
  "sarga": 4,
  "shloka_count": 35,
  "shlokas": [
    {
      "shloka": 1,
      "shloka_text": "ततः प्रहृष्टौ हनुमान्कृत्यवानिति तद्वचः। श्रुत्वा मधुरसम्भाषं  सुग्रीवं मनसा गतः4.4.1।।",
      "transliteration": "",
      "translation": "ततः then, कृत्यवान्  who has done his duty, हनुमान् Hanuman, इति thus, तद्वचः his words, श्रुत्वा having heard, मधुरसम्भाषं च and sweet talk, प्रहृष्टः glad, मनसा at heart, सुग्रीवम् to Sugriva, गतः about",
      "explanation": "After listening to the sweet words of Lakshmana, Hanuman, having done what he had to do felt happy and thought of Sugriva.",
      "telugu_translation": "లక్ష్మణుని మధురమైన మాటలు విన్న హనుమంతుడు తాను చేయవలసింది చేసిన తరువాత సంతోషించి సుగ్రీవుని తలచుకున్నాడు.",
      "comments": "Lakshmana speaks to Hanuman the purpose of their arrival at Rishyamuka -- Hanuman takes Rama and Lakshmana on his shoulders to Sugriva"
    },
    {
      "shloka": 2,
      "shloka_text": "भव्यो राज्यागमस्तस्य सुग्रीवस्य महात्मनः। यदयं कृत्यवान्प्राप्तः कृत्यं चैतदुपागतम्4.4.2।।",
      "transliteration": "",
      "translation": "महात्मनः great self, तस्य सुग्रीवस्य that Sugriva's, राज्यागमः acquisition of kingdom, भव्यः is likely to happen, यत् since, कृत्यवान्  one who has done his duty, अयम् this, प्राप्तः got, एतत् this, कृतं च and has work, उपागतम् has come",
      "explanation": "The great Sugriva, thinks Hanuman, who had done his duty is likely to acquire his kingdom, because great Rama who would help in the work of Sugriva has also come.'",
      "telugu_translation": "గొప్ప సుగ్రీవుడు, తన కర్తవ్యాన్ని నిర్వర్తించిన హనుమంతుడు తన రాజ్యాన్ని పొందే అవకాశం ఉందని భావిస్తాడు, ఎందుకంటే సుగ్రీవుడి పనిలో సహాయపడే గొప్ప రాముడు కూడా వచ్చాడు.",
      "comments": ""
    },
    {
      "shloka": 3,
      "shloka_text": "ततः परमसंहृष्टो हनुमान् प्लवगर्षभः। प्रत्युवाच ततो वाक्यं रामं वाक्यविशारदः4.4.3।।",
      "transliteration": "",
      "translation": "ततः then, परमसंहृष्टः extremely happy, प्लवगोत्तमः best of monkeys, हनुमान् Hanuman, ततः then,वाक्यविशारदम् learned in converasation, रामम् Rama's, वाक्यम् words, प्रत्युवाच  enquired",
      "explanation": "Hanuman, the best of the monkeys, learned in conversation, felt extremely happy and enquired from Rama:",
      "telugu_translation": "వానరులలో శ్రేష్ఠుడైన హనుమంతుడు సంభాషణను నేర్చుకున్నాడు, చాలా సంతోషించాడు మరియు రాముడిని ఇలా అడిగాడు:",
      "comments": ""
    },
    {
      "shloka": 4,
      "shloka_text": "किमिर्थं त्वं वनं घोरं पम्पाकाननमण्डितम्। आगतस्सानुजो दुर्गं नानाव्याळमृगायुतम्4.4.4।।",
      "transliteration": "",
      "translation": "सानुजः accompanied by your brother, पम्पाकाननमण्डितम् woods surrounding Pampa, दुर्गम् inaccessible, नानाव्यालमृगायुतम् full of different kinds of serpents and wild animals, घोरम् dreadful, वनम् forest, किमर्थम् why, आगतः came here?",
      "explanation": "'Why have you come with your brother to this dreadful, inaccessible forest surrounding Pampa, full of different varieties of serpents and wild animals?'",
      "telugu_translation": "'వివిధ రకాలైన సర్పాలు మరియు అడవి జంతువులతో నిండిన పంపా చుట్టూ ఉన్న ఈ భయంకరమైన, దుర్గమమైన అడవికి మీరు మీ సోదరుడితో ఎందుకు వచ్చారు?'",
      "comments": ""
    },
    {
      "shloka": 5,
      "shloka_text": "तस्य तद्वचनं श्रुत्वा लक्ष्मणो रामचोदितः। आचचक्षे महात्मानं रामं दशरथात्मजम्4.4.5।।",
      "transliteration": "",
      "translation": "लक्ष्मणः Lakshmana, तस्य his, तत् those, वचनम् words, श्रुत्वा having heard, रामचोदितः urged by Rama, महात्मानम् great soul, दशरथात्मजम् son of Dasaratha, रामम् Rama, आचचक्षे narrated",
      "explanation": "Having listened to Hanuman, and urged by Rama, Lakshmana told him about the great Rama, son of Dasaratha.",
      "telugu_translation": "హనుమంతుని మాట విని, రాముని కోరిన తరువాత, లక్ష్మణుడు దశరథుని కుమారుడైన గొప్ప రాముని గురించి అతనికి చెప్పాడు.",
      "comments": ""
    },
    {
      "shloka": 6,
      "shloka_text": "राजा दशरथो नाम द्युतिमान्धर्मवत्सलः। चातुर्वर्ण्यं स्वधर्मेण नित्यमेवाभ्यपालयत्4.4.6।।",
      "transliteration": "",
      "translation": "द्युतिमान् brilliant, धर्मवत्सलः lover of dharma, चातुर्वर्ण्यम् four classes, नित्यमेव always, स्वधर्मेण  his duty, अभ्यपालयत् ruled, दशरथो नाम named Dasaratha, राजा king",
      "explanation": "",
      "telugu_translation": "ద్యుతిమాన్ తెలివైనవాడు, ధర్మవత్సలః ధర్మ ప్రేమికుడు, చాతుర్వర్ణ్యం నాలుగు తరగతులు, నిత్యమేవ ఎల్లప్పుడూ, స్వధర్మే తన కర్తవ్యం, అలభ్యత, నియమం నామ పేరు దశరథుడు, రాజా రాజు",
      "comments": ""
    },
    {
      "shloka": 7,
      "shloka_text": "न द्वेष्टा विद्यते तस्य न च स द्वेष्टि कञ्चन। स च सर्वेषु भूतेषु पितामह इवापरः4.4.7।। अग्निष्टोमादिभिर्यज्ञैरिष्टवानाप्तदक्षिणैः।",
      "transliteration": "",
      "translation": "तस्य his, द्वेष्टा enemy, न विद्यते never existed, सः he, कञ्चन any one indeed, न द्वेष्टि not hated, सः he, सर्वेषु at all, भूतेषु beings, अपरः another, पितामहः इव like the father, आप्तदक्षिणैः with generous gifts, अग्निष्टोमादिभिः with fire sacrifices and others, यज्ञैः with yajnas, इष्टवान् performed.",
      "explanation": "'He never hated any one nor did any one ever hate him. To all his subjects, he was like another father, the Creator Brahma. And he was generous in giving gifts while performing yajnas (rituals with fire) like Agnistoma.",
      "telugu_translation": "'అతను ఎవ్వరినీ ద్వేషించలేదు, ఎవరూ అతనిని ద్వేషించలేదు. తన ప్రజలందరికీ, అతను మరొక తండ్రి, సృష్టికర్త బ్రహ్మ వంటివాడు. మరియు అతను అగ్నిస్తోమా వంటి యజ్ఞాలు (అగ్నితో కర్మలు) చేస్తున్నప్పుడు బహుమతులు ఇవ్వడంలో ఉదారంగా ఉండేవాడు.",
      "comments": ""
    },
    {
      "shloka": 8,
      "shloka_text": "तस्यायं पूर्वजः पुत्रो रामो नाम जनैः श्रुतः।।4.4.8।। शरण्यस्सर्वभूतानां पितुर्निर्देशपारगः।",
      "transliteration": "",
      "translation": "अयम् this is, तस्य his, पूर्वजः elder, पुत्रः son, रामो नाम by name Rama, जनैः by people, श्रुतः popular, सर्वभूतानाम् at all beings, शरण्यः protector, पितुः father's, निर्देशपारगः one who  never fails to follow instructions.",
      "explanation": "'Here is his eldest son, popularly known as Rama. He is the protector of all beings and never failed his father's instructions.",
      "telugu_translation": "'రాముడుగా ప్రసిద్ధి చెందిన అతని పెద్ద కుమారుడు ఇక్కడ ఉన్నాడు. అతను అన్ని జీవులకు రక్షకుడు మరియు తన తండ్రి సూచనలను ఎప్పుడూ విఫలం చేయలేదు.",
      "comments": ""
    },
    {
      "shloka": 9,
      "shloka_text": "वीरो दशरथस्यायं पुत्राणां गुणवत्तमः।।4.4.9।। राजलक्षणसम्पन्नस्सम्युक्तो राजसम्पदा। राज्याद्भ्रष्टो वने वस्तुं मया सार्धमिहागतः4.4.10।।",
      "transliteration": "",
      "translation": "दशरथस्य Dasaratha's, पुत्राणाम् among sons, वीरः warrior, गुणवत्तमः most virtuous, राजलक्षणसंयुक्तः endowed with royal traits, राज्यसम्पदा with royal wealth, संयुक्तः he is endowed with, अयम् this one, राज्यात् from kingdom, भ्रष्टः is sent away, वने in the forest, वस्तुम् to reside, मया सार्धम् along with me, इह here, आगतः has come",
      "explanation": "",
      "telugu_translation": "దశరథస్య దశరథుని, పుత్రులలో పుత్రనామ్, వీరః యోధుడు, గుణవత్తమః అత్యంత సద్గుణవంతుడు, రాజలక్షణసంయుక్తః ప్రసాదించిన రాజ్యసంపద రాజ సంపదతో, సంయుక్తః ఇతడు ప్రసాదించబడ్డాడు, అయమ్ ఇతడు, రాజ్యం నుండి రాజ్యం, భ్రష్టః దూరంగా పంపబడ్డాడు, అడవిలో వనే, రమ్య నివాసానికి నాతో పాటు, ఇహ ఇక్కడ, ఆగతః వచ్చింది",
      "comments": ""
    },
    {
      "shloka": 10,
      "shloka_text": "वीरो दशरथस्यायं पुत्राणां गुणवत्तमः।।4.4.9।। राजलक्षणसम्पन्नस्सम्युक्तो राजसम्पदा। राज्याद्भ्रष्टो वने वस्तुं मया सार्धमिहागतः4.4.10।।",
      "transliteration": "",
      "translation": "दशरथस्य Dasaratha's, पुत्राणाम् among sons, वीरः warrior, गुणवत्तमः most virtuous, राजलक्षणसंयुक्तः endowed with royal traits, राज्यसम्पदा with royal wealth, संयुक्तः he is endowed with, अयम् this one, राज्यात् from kingdom, भ्रष्टः is sent away, वने in the forest, वस्तुम् to reside, मया सार्धम् along with me, इह here, आगतः has come",
      "explanation": "",
      "telugu_translation": "దశరథస్య దశరథుని, పుత్రులలో పుత్రనామ్, వీరః యోధుడు, గుణవత్తమః అత్యంత సద్గుణవంతుడు, రాజలక్షణసంయుక్తః ప్రసాదించిన రాజ్యసంపద రాజ సంపదతో, సంయుక్తః ఇతడు ప్రసాదించబడ్డాడు, అయమ్ ఇతడు, రాజ్యం నుండి రాజ్యం, భ్రష్టః దూరంగా పంపబడ్డాడు, అడవిలో వనే, రమ్య నివాసానికి నాతో పాటు, ఇహ ఇక్కడ, ఆగతః వచ్చింది",
      "comments": ""
    },
    {
      "shloka": 11,
      "shloka_text": "भार्यया च महातेजास्सीतयाऽनुगतो वशी। दिनक्षये महातेजाः प्रभयेव दिवाकरः4.4.11।।",
      "transliteration": "",
      "translation": "महातेजाः glorious one, वशी selfcontrolled, दिनक्षये at the end of the day, दिवाकरः Sun, प्रभयेव with radiance, भार्यया  with wife, सीतया with Sita, अनुगतः followed",
      "explanation": "'This glorious Rama was followed by his wife, Sita, like the rays of the effulgent Sun follow him to the end of the day.",
      "telugu_translation": "'ఈ మహిమాన్విత రాముడిని అతని భార్య సీత, ప్రకాశించే సూర్యుని కిరణాలు రోజు చివరి వరకు అతనిని అనుసరిస్తాయి.",
      "comments": ""
    },
    {
      "shloka": 12,
      "shloka_text": "अहमस्यावरो भ्राता गुणैर्दास्यमुपागतः। कृतज्ञस्य बहुज्ञस्य लक्ष्मणो नाम नामतः4.4.12।।",
      "transliteration": "",
      "translation": "अहम् I am, कृतज्ञस्य of the grateful man, बहुज्ञस्य of a wellversed man, अस्य his, गुणैः by virtues, दास्यम् servitude, उपागतः has accepted, अवरः younger, भ्राता brother, नामतः  name, लक्ष्मणो नाम called Lakshmana",
      "explanation": "'I am his younger brother, called Lakshmana. I have accepted the service of this learned, virtuous and grateful man.",
      "telugu_translation": "'నేను అతని తమ్ముడిని, లక్ష్మణుడు. ఈ పండితుడు, సద్గుణవంతుడు మరియు కృతజ్ఞత గల వ్యక్తి యొక్క సేవను నేను అంగీకరించాను.",
      "comments": ""
    },
    {
      "shloka": 13,
      "shloka_text": "सुखार्हस्य महार्हस्य सर्वभूतहितात्मनः। ऐश्वर्येण च हीनस्य वनवासाश्रितस्य च4.4.13।। रक्षसाऽपहृता भार्या रहिते कामरूपिणा। तच्च न ज्ञायते रक्षः पत्नी येनास्य सा हृता4.4.14।।",
      "transliteration": "",
      "translation": "सुखार्हस्य  deserved comforts, महार्हस्य worthy  of reverence, सर्वभूतहितात्मनः wellwisher of all beings, ऐश्वर्येण by wealth, विहीनस्य deprived, वनवासे dwelling in the forest, रतस्य of a man engaged, भार्या wife, रहिते when we were not present2 2सा she, कामरूपिणा who can assume any form at will, रक्षसा by a demon, अपहृता kidnapped, येन वा or by whomsoever,  अस्य his, भार्या wife, हृता has been stolen, तत् that, रक्षः rakshasa, न ज्ञायते is not known",
      "explanation": "'This man who should have lived in comfort and in reverence, one who was worthy of all the wellwishers lost his wealth and was banished into the forest. He is now deprived of his wife kidnapped by an unknown demon who could assume any form at will.",
      "telugu_translation": "'సౌఖ్యంగా, భక్తితో జీవించాల్సిన ఈ వ్యక్తి, శ్రేయోభిలాషులందరికీ యోగ్యుడైన వ్యక్తి తన సంపదను కోల్పోయి అడవికి వెళ్లగొట్టబడ్డాడు. అతను ఇప్పుడు తన భార్యను తెలియని దెయ్యం చేత కిడ్నాప్ చేయబడ్డాడు, అతను ఇష్టానుసారం ఏ రూపాన్ని అయినా ధరించగలడు.",
      "comments": ""
    },
    {
      "shloka": 14,
      "shloka_text": "सुखार्हस्य महार्हस्य सर्वभूतहितात्मनः। ऐश्वर्येण च हीनस्य वनवासाश्रितस्य च4.4.13।। रक्षसाऽपहृता भार्या रहिते कामरूपिणा। तच्च न ज्ञायते रक्षः पत्नी येनास्य सा हृता4.4.14।।",
      "transliteration": "",
      "translation": "सुखार्हस्य  deserved comforts, महार्हस्य worthy  of reverence, सर्वभूतहितात्मनः wellwisher of all beings, ऐश्वर्येण by wealth, विहीनस्य deprived, वनवासे dwelling in the forest, रतस्य of a man engaged, भार्या wife, रहिते when we were not present2 2सा she, कामरूपिणा who can assume any form at will, रक्षसा by a demon, अपहृता kidnapped, येन वा or by whomsoever,  अस्य his, भार्या wife, हृता has been stolen, तत् that, रक्षः rakshasa, न ज्ञायते is not known",
      "explanation": "'This man who should have lived in comfort and in reverence, one who was worthy of all the wellwishers lost his wealth and was banished into the forest. He is now deprived of his wife kidnapped by an unknown demon who could assume any form at will.",
      "telugu_translation": "'సౌఖ్యంగా, భక్తితో జీవించాల్సిన ఈ వ్యక్తి, శ్రేయోభిలాషులందరికీ యోగ్యుడైన వ్యక్తి తన సంపదను కోల్పోయి అడవికి వెళ్లగొట్టబడ్డాడు. అతను ఇప్పుడు తన భార్యను తెలియని దెయ్యం చేత కిడ్నాప్ చేయబడ్డాడు, అతను ఇష్టానుసారం ఏ రూపాన్ని అయినా ధరించగలడు.",
      "comments": ""
    },
    {
      "shloka": 15,
      "shloka_text": "दनुर्नाम दितेः पुत्रश्शापाद्राक्षसतां गतः। आख्यातस्तेन सुग्रीवस्समर्थो वानरर्षभः4.4.15।।",
      "transliteration": "",
      "translation": "दितेः Diti's, पुत्रः a son, शापात् by curse, राक्षसताम् as a demon, गतः became, दनुः नाम called Danu, तेन by him, वानरर्षभः the bull among monkeys, सुग्रीवः Sugriva, समर्थः capable, आख्यातः had said",
      "explanation": "'Diti's son called Danu who had been cursed to live the life of a demon had said that Sugriva, the best among monkeys, would be able to locate her.",
      "telugu_translation": "'వానరులలో శ్రేష్ఠుడైన సుగ్రీవుడు ఆమెను గుర్తించగలడని రాక్షసుడిలా జీవించమని శాపగ్రస్తుడైన దనుడు అనే దితి కుమారుడు చెప్పాడు.",
      "comments": ""
    },
    {
      "shloka": 16,
      "shloka_text": "स ज्ञास्यति महावीर्यस्तव भार्यापहारिणम्। एवमुक्त्वा दनुस्स्वर्गं भ्राजमानो गतस्सुखम्4.4.16।।",
      "transliteration": "",
      "translation": "महावीर्यः valiant one, सः he, तव your, भार्यापहारिणम्  who has stolen your wife, ज्ञास्यति will know, दनुः Danu, एवम् in that way, उक्त्वा having said, भ्राजमानः glowing away, स्वर्गम् heaven, सुखम् happily, गतः went",
      "explanation": "'That Valiant Sugriva can spot the demon who has abducted your wife', said Danu and disappeared happily into heaven shining in brilliance.",
      "telugu_translation": "'నీ భార్యను అపహరించిన రాక్షసుడిని ఆ పరాక్రమవంతుడు సుగ్రీవుడు గుర్తించగలడు' అని దనువు తేజస్సుతో ప్రకాశిస్తూ స్వర్గానికి ఆనందంగా అదృశ్యమయ్యాడు.",
      "comments": ""
    },
    {
      "shloka": 17,
      "shloka_text": "एतत्ते सर्वमाख्यातं यथा तथ्येन पृच्छतः। अहं चैव हि रामश्च सुग्रीवं शरणं गतौ4.4.17।।",
      "transliteration": "",
      "translation": "पृच्छतः since you asked, ते you, एतत् that, सर्वम् every event, यथा तथ्येन  in fact, आख्यातम् said, अहं चैव and I also, रामश्च Rama too, सुग्रीवम् Sugriva's, शरणम् refuge, गतौ both arrived",
      "explanation": "'I have given a factual account of everything, since you asked me. Now Rama and I have arrived seeking Sugriva's shelter.",
      "telugu_translation": "'మీరు నన్ను అడిగినప్పటి నుండి నేను ప్రతిదానికీ వాస్తవిక ఖాతా ఇచ్చాను. ఇప్పుడు రాముడు మరియు నేను సుగ్రీవుని ఆశ్రయం కోరుతూ వచ్చాము.",
      "comments": ""
    },
    {
      "shloka": 18,
      "shloka_text": "एष दत्त्वा च वित्तानि प्राप्य चानुत्तमं यशः। लोकनाथः पुरा भूत्वा सुग्रीवं नाथमिच्छति4.4.18।।",
      "transliteration": "",
      "translation": "एषः this person, वित्तानि wealth, दत्त्वा च and gifting , अनुत्तमम् excellence ,यशः fame, प्राप्य च having obtained, पुरा earlier, लोकनाथः lord of the world, सुग्रीवम् Sugriva, नाथम् king, इच्छति wishes",
      "explanation": "'Having earned supreme fame through his munificence in the past, this lord of the world now craves Sugriva's indulgence.",
      "telugu_translation": "'గతంలో తన మునిపనుల ద్వారా అత్యున్నతమైన కీర్తిని సంపాదించిన ఈ లోక ప్రభువు ఇప్పుడు సుగ్రీవుని భోగభాగ్యాలను కోరుతున్నాడు.",
      "comments": ""
    },
    {
      "shloka": 19,
      "shloka_text": "पिता यस्य पुरा ह्यासीच्छरण्यो धर्मवत्सलः। तस्य पुत्रश्शरण्यश्च सुग्रीवं शरणं गतः4.4.19।।",
      "transliteration": "",
      "translation": "पुरा earlier, यस्य whose, धर्मवत्सलः lover of dharma, पिता father, शरण्यः refuge to others, आसीत् he was, शरण्यश्च refuge of, तस्य his, पुत्रः son, सुग्रीवम् to Sugriva, शरणं गतः seeks protection",
      "explanation": "'One whose father was once a protector of dharma, a refuge to all now seeks Sugriva's shelter.",
      "telugu_translation": "'ఒకప్పుడు ఎవరి తండ్రి ధర్మ రక్షకుడో, అందరికీ ఆశ్రయమిచ్చేవాడు ఇప్పుడు సుగ్రీవుని ఆశ్రయం పొందుతున్నాడు.",
      "comments": ""
    },
    {
      "shloka": 20,
      "shloka_text": "सर्वलोकस्य धर्मात्मा शरण्यश्शरणं पुरा। गुरुर्मे राघवस्सोऽयं सुग्रीवं शरणं गतः4.4.20।।",
      "transliteration": "",
      "translation": "धर्मात्मा righteous, शरण्यः  protector, पुरा earlier, सर्वलोकस्य for the whole world, to all (his) people शरणम् protector, गुरुः respectable, सः he, अयम् this person, राघवः Rama, सुग्रीवम् Sugriva's, शरणं गतः sought protection",
      "explanation": "'This righteous Rama who used to lend in the past protection to the whole world and, indeed, a refuge to all, venerable sir, now seeks Sugriva's shelter.",
      "telugu_translation": "'పూర్వజన్మలో సమస్త జగత్తుకు రక్షణ కల్పించి, అందరికీ ఆశ్రయమిచ్చిన ఈ ధర్మాత్ముడైన రాముడు ఇప్పుడు సుగ్రీవుని ఆశ్రయం పొందుతున్నాడు.",
      "comments": ""
    },
    {
      "shloka": 21,
      "shloka_text": "यस्य प्रसादे सततं प्रसीदेयुरिमाः प्रजाः। स रामो वानरेन्द्रस्य प्रसादमभिकाङ्क्षते। 4.4.21।।",
      "transliteration": "",
      "translation": "यस्य whose, प्रसादे grace, इमाः these, प्रजाः people, सततम् always, प्रसीदेयुः they will be pleased, सः रामः that Rama, वानरेन्द्रस्य chief of monkeys', प्रसादम् favour, अभिकाङ्क्षते is desiring",
      "explanation": "'This Rama for whose grace the subjects were ever bobolden to him now seeks the favour of the Chief of monkeys.",
      "telugu_translation": "'ఈ రాముడు ఎవరి అనుగ్రహం కోసం అతనికి ఎప్పుడూ బోల్డ్‌గా ఉన్నాడో ఇప్పుడు వానరుల అధిపతిని కోరుతున్నాడు.",
      "comments": ""
    },
    {
      "shloka": 22,
      "shloka_text": "येन सर्वगुणोपेताः पृथिव्यां सर्वपार्थिवाः। मानितास्सततं राज्ञा सदा दशरथेन वै4.4.22 तस्यायं पूर्वजः पुत्रस्त्रिषु लोकेषु विश्रुतः। सुग्रीवं वानरेन्द्रं तु रामश्शरणमागतः4.4.23।।",
      "transliteration": "",
      "translation": "राज्ञा by the king, येन by whom, दशरथेन by Dasaratha, पृथिव्याम् on this earth, सर्वगुणोपेताः endowed with all virtues, सर्वपार्थिवाः all kings, सदा always, सततम् ever, मानिताः honoured, तस्य his, पूर्वजः eldest, पुत्रः son, त्रिषु लोकेषु in the three worlds, विश्रुतः very famous, अयं रामः such Rama,  वानरेन्द्रम् lord of monkeys, सुग्रीवम् Sugriva, शरणमागतः sought refuge",
      "explanation": "'Famous in all the three worlds, this Rama, who was the firshborn of Dasaratha, endowed with all virtues and ever respected by all the kings of this earth, now seeks shelter of Sugriva, Chief of monkeys.",
      "telugu_translation": "'మూడు లోకములలో ప్రసిద్ధుడైన, దశరథునికి ముద్దుబిడ్డ, సకల గుణ సంపన్నుడైన, ఈ భూలోకంలోని రాజులందరిచే గౌరవింపబడిన ఈ రాముడు ఇప్పుడు వానర అధిపతి అయిన సుగ్రీవుని ఆశ్రయిస్తున్నాడు.",
      "comments": ""
    },
    {
      "shloka": 23,
      "shloka_text": "येन सर्वगुणोपेताः पृथिव्यां सर्वपार्थिवाः। मानितास्सततं राज्ञा सदा दशरथेन वै4.4.22 तस्यायं पूर्वजः पुत्रस्त्रिषु लोकेषु विश्रुतः। सुग्रीवं वानरेन्द्रं तु रामश्शरणमागतः4.4.23।।",
      "transliteration": "",
      "translation": "राज्ञा by the king, येन by whom, दशरथेन by Dasaratha, पृथिव्याम् on this earth, सर्वगुणोपेताः endowed with all virtues, सर्वपार्थिवाः all kings, सदा always, सततम् ever, मानिताः honoured, तस्य his, पूर्वजः eldest, पुत्रः son, त्रिषु लोकेषु in the three worlds, विश्रुतः very famous, अयं रामः such Rama,  वानरेन्द्रम् lord of monkeys, सुग्रीवम् Sugriva, शरणमागतः sought refuge",
      "explanation": "'Famous in all the three worlds, this Rama, who was the firshborn of Dasaratha, endowed with all virtues and ever respected by all the kings of this earth, now seeks shelter of Sugriva, Chief of monkeys.",
      "telugu_translation": "'మూడు లోకములలో ప్రసిద్ధుడైన, దశరథునికి ముద్దుబిడ్డ, సకల గుణ సంపన్నుడైన, ఈ భూలోకంలోని రాజులందరిచే గౌరవింపబడిన ఈ రాముడు ఇప్పుడు వానర అధిపతి అయిన సుగ్రీవుని ఆశ్రయిస్తున్నాడు.",
      "comments": ""
    },
    {
      "shloka": 24,
      "shloka_text": "शोकाभिभूते रामे तु शोकार्ते शरणं गते। कर्तुमर्हति सुग्रीवः प्रसादं हरियूधपः4.4.24।।",
      "transliteration": "",
      "translation": "हरियूधप: lord of monkeys, शोकाभिभूते one who is overcome by grief, शोकार्ते one who is pained  by sorrow, शरणं गते when he sought refuge, रामे to Rama, सुग्रीवः Sugriva, प्रसादम्  favour कर्तुम् to render, अर्हति deserves",
      "explanation": "'Sugriva, lord of monkeys, ought to help Rama who tormented by, and overwhelmed with, grief seeks his favour.'",
      "telugu_translation": "'సుగ్రీవుడు, వానరుల ప్రభువు, తన అనుగ్రహాన్ని కోరుతూ, దుఃఖంతో బాధపడ్డ రాముడికి సహాయం చేయాలి.",
      "comments": ""
    },
    {
      "shloka": 25,
      "shloka_text": "एवं ब्रुवाणं सौमित्रिं करुणं साश्रुलोचनम्। हनुमान्प्रत्युवाचेदं वाक्यं वाक्यविशारदः4.4.25।।",
      "transliteration": "",
      "translation": "करुणम् piteously, साश्रुलोचनम् eyes filled with tears, एवम् that way, ब्रुवाणम् while speaking, सौमित्रिम् to Saumithri, वाक्यविशारदः an erudite speaker, हनुमान् Hanuman, इदम् these, वाक्यम् words, प्रत्युवाच replied back",
      "explanation": "To Saumitri who was speaking thus in a piteous tone, his eyes filled with tears the eloquent Hanuman replied:",
      "telugu_translation": "దీన స్వరంతో ఇలా మాట్లాడుతున్న సౌమిత్రికి, అతని కళ్ళు నీళ్లతో నిండిపోయాయి, అనర్గళుడైన హనుమంతుడు ఇలా సమాధానమిచ్చాడు:",
      "comments": ""
    },
    {
      "shloka": 26,
      "shloka_text": "ईदृशा बुद्धिसम्पन्ना जितक्रोधा जितेन्द्रियाः। द्रष्टव्या वानरेन्द्रेण दिष्ट्या दर्शनमागताः4.4.26।।",
      "transliteration": "",
      "translation": "बुद्धिसम्पन्नाः highly intelligent, जितक्रोधाः who have conquered anger, जितेन्द्रियाः who have 2 2conquered senses, दिष्ट्या luckily, दर्शनम् to see, आगताः came here, ईदृशाः such men, वानरेन्द्रेण by king of vanaras, द्रष्टव्या deserve to be approached",
      "explanation": "'It is a matter of great fortune that you who have intelligence, control over your senses and conquered anger have come to see the lord of monkeys who needs instead, to approach you.",
      "telugu_translation": "'తెలివి, ఇంద్రియాలపై నియంత్రణ, కోపాన్ని జయించిన మీరు బదులుగా అవసరమైన వానరుల స్వామిని చూడడానికి, మీ దగ్గరకు రావడానికి రావడం గొప్ప అదృష్టం.",
      "comments": ""
    },
    {
      "shloka": 27,
      "shloka_text": "स हि राज्यात्परिभ्रष्टः कृतवैरश्च वालिना। हृतदारो वने त्यक्तो भ्रात्रा विनिकृतो भृशम्4.4.27।।",
      "transliteration": "",
      "translation": "वालिना by Vali, कृतवैरः developed enmity, भ्रात्रा by his brother, हृतदारः deprived of his wife, भृशम् strongly, विनिकृतः is offended, राज्यात् from the kingdom, विभ्रष्टः thrown out, सः he, त्यक्त: is abandoned, वने in the forest",
      "explanation": "'(In fact) seriously offended by his brother Vali who treated him like his enemy and expelled him from the kingdom. He is now abandoned in the forest, his wife hijacked.",
      "telugu_translation": "'(వాస్తవానికి) అతని సోదరుడు వాలితో తీవ్రంగా మనస్తాపం చెంది అతనిని తన శత్రువులా భావించి రాజ్యం నుండి బహిష్కరించాడు. అతను ఇప్పుడు అడవిలో వదిలివేయబడ్డాడు, అతని భార్య హైజాక్ చేయబడింది.",
      "comments": ""
    },
    {
      "shloka": 28,
      "shloka_text": "करिष्यति स साहाय्यं युवयोर्भास्करात्मजः। सुग्रीवस्सह चास्माभि स्सीतायाः परिमार्गणे4.4.28।।",
      "transliteration": "",
      "translation": "भास्करात्मजः son of the Sungod, सुग्रीवः Sugriva, अस्माभिः सह along with us, सीतायाः Sita's, परिमार्गणे in search of, युवयोः for both of you, साहाय्यम् help, करिष्यति he will do",
      "explanation": "'Sugriva, son of the Sungod, along with us will extend all help to you, in your search for Sita.'",
      "telugu_translation": "'సుగ్రీవుడు, సుంగోద్ కుమారుడూ, మాతో పాటు, సీతను వెతకడానికి మీకు అన్ని విధాలుగా సహాయం చేస్తారు.'",
      "comments": ""
    },
    {
      "shloka": 29,
      "shloka_text": "इत्येवमुक्त्वा हनुमान् श्लक्ष्णं मधुरया गिरा। बभाषे सोऽभिगच्छेम सुग्रीवमिति राघवम्4.4.29।।",
      "transliteration": "",
      "translation": "हनुमान् Hanuman, मधुरया sweetly, गिरा with words, इत्येवम् like that, श्लक्ष्णम् gently, उक्त्वा having said, साधु well done, सुग्रीवम् to Sugriva, अभिगच्छेम we will go, इति thus, राघवम् Raghava, बभाषे spoke",
      "explanation": "Hanuman, having spoken with sweet, gentle words said to the Raghavas, 'We will now go to Sugriva'.",
      "telugu_translation": "హనుమంతుడు మధురమైన, సౌమ్యమైన మాటలతో మాట్లాడి రాఘవులతో, 'మనం ఇప్పుడు సుగ్రీవుని వద్దకు వెళ్తాము' అని చెప్పాడు.",
      "comments": ""
    },
    {
      "shloka": 30,
      "shloka_text": "एवं ब्रुवाणं धर्मात्मा हनुमन्तं स लक्ष्मणः। प्रतिपूज्य यथान्यायमिदं प्रोवाच राघवम्4.4.30।।",
      "transliteration": "",
      "translation": "धर्मात्मा righteous, सः लक्ष्मणः that Lakshmana, एवम् in that way, ब्रुवाणम् as he spoke, हनुमन्तम् to Hanuman, यथान्यायम् as per tradition, प्रतिपूज्य  offered salutation, राघवम् Raghava, इदम् this, प्रोवाच spoke",
      "explanation": "Having offered reverential salutations to Hanuman as per tradition, righteous Lakshmana now spoke to Rama:",
      "telugu_translation": "సంప్రదాయం ప్రకారం హనుమంతునికి పూజ్య నమస్కారాలు చేసి, నీతిమంతుడైన లక్ష్మణుడు ఇప్పుడు రామునితో ఇలా అన్నాడు:",
      "comments": ""
    },
    {
      "shloka": 31,
      "shloka_text": "कपिः कथयते हृष्टो यथाऽयं मारुतात्मजः। कृत्यवांत्सोऽपि सम्प्राप्तः कृतकृत्योऽसि राघव4.4.31।।",
      "transliteration": "",
      "translation": "राघव Rama, मारुतात्मजः son of the windgod, अयं कपिः this monkey, हृष्टः a pleased one, यथा as, कथयते he is telling, सोऽपि he also, कृत्यवान् a person of action, सम्प्राप्तः has come, कृतकृत्यः  accomplished, असि you are",
      "explanation": "'O Raghava this monkey, son of the Windgod appears pleased as evident from his words. As he is a man of action, take your work as accomplished now.",
      "telugu_translation": "'ఓ రాఘవా, ఈ కోతి, వాయుదేవుని కుమారుడా, అతని మాటలను బట్టి ప్రస్ఫుటంగా కనిపిస్తుంది. అతను చర్య తీసుకునే వ్యక్తి కాబట్టి, మీ పనిని ఇప్పుడే పూర్తి చేయండి.",
      "comments": ""
    },
    {
      "shloka": 32,
      "shloka_text": "प्रसन्नमुखवर्णश्च व्यक्तं हृष्टश्च भाषते। नानृतं वक्ष्यते वीरो हनुमान्मारुतात्मजः4.4.32।।",
      "transliteration": "",
      "translation": "व्यक्तम् it is evident, प्रसन्नमुखवर्णश्च he has a cheerful face, हृष्टश्च he is pleased, भाषते  words, मारुतात्मजः son of the windgod, हनुमान् Hanuman, अनृतम् lie, न वक्ष्यते will not tell",
      "explanation": "'It is evident from his words  and from his cheerful face that Hanuman is pleased. (I know that) this heroic son of the Windgod will never tell a lie'.",
      "telugu_translation": "'హనుమంతుడు ప్రసన్నుడయ్యాడని అతని మాటలను బట్టి, అతని ప్రసన్న ముఖాన్ని బట్టి తెలుస్తుంది. (నాకు తెలుసు) ఈ వీరాభిమానుడైన వాయుదేవుడు ఎప్పటికీ అబద్ధం చెప్పడు.",
      "comments": ""
    },
    {
      "shloka": 33,
      "shloka_text": "ततस्स तु महाप्राज्ञो हनुमान्मारुतात्मजः। जगामादाय तौ वीरौ हरिराजाय राघवौ4.4.33।।",
      "transliteration": "",
      "translation": "ततः then, महाप्राज्ञः very wise, मारुतात्मजः son of the windgod, सः हनुमान् that Hanuman, वीरौ   warrior heroes, तौ राघवौ both Raghavas, हरिराजाय to the king of monkeys, आदाय led them, जगाम went",
      "explanation": "Hanuman, son of the Windgod, endowed with great wisdom carried both the Raghava warriors to the king of monkeys.",
      "telugu_translation": "వానదేవుని కుమారుడైన హనుమంతుడు రాఘవ యోధులిద్దరినీ వానర రాజు వద్దకు తీసుకువెళ్లాడు.",
      "comments": ""
    },
    {
      "shloka": 34,
      "shloka_text": "भिक्षुरूपं परित्यज्य वानरं रूपमास्थितः। पृष्ठमारोप्य तौ वीरौ जगाम कपिकुञ्जरः4.4.34।।",
      "transliteration": "",
      "translation": "कपिकुञ्जरः elephantlike monkey, भिक्षुरूपम् form of a mendicant, परित्यज्य  gave up, वानरम् monkeys, रूपम् form, आस्थितः assumed, तौ both, वीरौ heroes, पृष्ठम् on the back, आरोप्य lifted, जगाम proceeded.",
      "explanation": "Hanuman, who was an elephant among monkeys, gave up the guise of a mendicant, and assuming the form of the monkeys, lifted both the heroes  on to his back and proceeded.",
      "telugu_translation": "వానరులలో ఏనుగుగా ఉన్న హనుమంతుడు దూషకుడి వేషాన్ని విడిచిపెట్టి, కోతుల రూపాన్ని ధరించి, వీరిద్దరినీ తన వీపుపైకి ఎత్తుకుని ముందుకు సాగాడు.",
      "comments": ""
    },
    {
      "shloka": 35,
      "shloka_text": "स तु विपुलयशाः कपिप्रवीरः पवनसुतः कृतकृत्यवत्प्रहृष्टः। गिरिवरमुरुविक्रमः प्रयात स्स शुभमतिस्सह रामलक्ष्मणाभ्याम्4.4.35।।",
      "transliteration": "",
      "translation": "विपुलयशाः highly renowned, कपिप्रवीरः most heroic monkey, सः पवनसुतः son of the windgod, कृतकृत्यवत् having done his duty, प्रहृष्टः gladly, शुभमतिः with auspicious feeling, उरुविक्रमः renowned for his valiance, सः he, रामलक्ष्मणाभ्यां सह with Rama and Lakshmana, गिरिवरम् to the great mountain, प्रयातः departed.",
      "explanation": "The son of the Windgod, the most valiant, the supremely heroic monkey and the one welladmired, having performed his task, felt immensely happy.And with an auspicious feeling, departed for the great mountain (Rishyamuka) along with Rama and Lakshmana. इत्यार्षे श्रीमद्रामायणे वाल्मीकीय आदिकाव्ये किष्किंधाकाण्डे चतुर्थस्सर्गः।। Thus ends the fourth sarga of Kishkindakanda of the Holy Ramayana, the first epic composed by sage Valmiki.",
      "telugu_translation": "వాయుదేవుని కుమారుడు, అత్యంత పరాక్రమవంతుడు, అత్యద్భుతమైన పరాక్రమవంతుడు మరియు బాగా మెచ్చిన వానరుడు, తన కార్యాన్ని నిర్వర్తించి, ఎంతో ఆనందాన్ని పొందాడు. మరియు ఒక శుభ భావనతో, రాముడు మరియు లక్ష్మణులతో కలిసి గొప్ప పర్వతం (ఋష్యమూక) వైపు బయలుదేరాడు. ఇత్యార్షే శ్రీమద్రామాయణే వాల్మీకీయ ఆదికావ్యే కిష్కింధాకాణ్డే చతుర్థస్సర్. వాల్మీకి మహర్షి రచించిన మొదటి ఇతిహాసం పవిత్ర రామాయణంలోని కిష్కిందకాండలోని నాల్గవ సర్గ ఇలా ముగుస్తుంది.",
      "comments": ""
    }
  ]
}