{
  "kanda": "Yuddha Kanda",
  "kanda_slug": "yuddha-kanda",
  "sarga": 30,
  "shloka_count": 35,
  "shlokas": [
    {
      "shloka": 1,
      "shloka_text": "ततस्तमक्षोभ्यबलंलङ्काधिपतयेचराः । सुवेलेराघवंशैलेनिविष्टंप्रत्यवेदयन् ।।6.30.1।।",
      "transliteration": "",
      "translation": "तत thereafter, चरा the spies, अक्षोभ्यबलम् unshakable army, तम् them, राघवम् Raghava, सुवेलेशैले Suvela mountain, निविष्टम् camped, लङ्काधिपतये to the king of Lanka, प्रत्यवेदयन् reported.",
      "explanation": "Thereafter, the spies reported to the king of Lanka that Raghava had camped with an unshakable army at the Suvela mountain.",
      "telugu_translation": "ఆ తరువాత, రాఘవ సువేల పర్వతం వద్ద అస్థిరమైన సైన్యంతో విడిది చేసినట్లు గూఢచారులు లంకా రాజుకు నివేదించారు.",
      "comments": "Saardula gives detailed descriptions of the Vanara army to Ravana."
    },
    {
      "shloka": 2,
      "shloka_text": "चाराणांरावणश्श्रुत्वाप्राप्तंरामंमहाबलम् । जातोद्वेगोऽभवत्किञ्चिच्छार्दूलंवाक्यमब्रवीत् ।।6.30.2।।",
      "transliteration": "",
      "translation": "रावण Ravana, महाबलम् great army, रामम् Rama, प्राप्तम् has camped, चाराणाम् from Spies, श्रुत्वा having heard, किञ्चित् a little, जातोद्वेग felt panicky, अभवत् became, शार्दूलम् to Saardula, वाक्यम् these words, अब्रवीत् said.",
      "explanation": "On hearing from the spies that Rama has camped with a great army, Ravana got a little panicky and said these words to Saardula.",
      "telugu_translation": "రాముడు గొప్ప సైన్యంతో విడిది చేశాడని గూఢచారుల నుండి విన్న రావణుడు కొంచెం భయాందోళనకు గురయ్యాడు మరియు శార్దూలతో ఈ మాటలు చెప్పాడు.",
      "comments": ""
    },
    {
      "shloka": 3,
      "shloka_text": "अयथावच्चतेवर्णोदीनश्चासिनिशाचर । नासिकच्चिदमित्राणांक्रुद्धानांवशमागतः ।।6.30.3।।",
      "transliteration": "",
      "translation": "निशाचर forest ranger, ते your, वर्ण colour (face colour), आयथावत् च as it should be, दीनश्च piteous, अपि and also, क्रुद्धानाम् angry, अमित्राणाम् enemies, वशम् side, नआगतःकच्चित् not come to you and done anything.",
      "explanation": "\"O Forest ranger! Your face is not as it should be and also pitiable. Hope the angry enemies have not done anything to you.\"",
      "telugu_translation": "\"ఓ ఫారెస్ట్ రేంజర్! నీ ముఖం ఎలా ఉండాలో అలాగే దయనీయంగా లేదు. కోపంతో ఉన్న శత్రువులు నిన్ను ఏమీ చేయలేదని ఆశిస్తున్నాను.\"",
      "comments": ""
    },
    {
      "shloka": 4,
      "shloka_text": "इतितेनानुशिष्टस्तुवाचंमन्दमुदीरयत् । तदाराक्षसशार्दूलंशार्दूलोभयविह्वलः ।।6.30.4।।",
      "transliteration": "",
      "translation": "इति and then, तेन by him, अनुशिष्ट questioned, भयविह्वल overwhelmed by fear, शार्दूल to Saardula, तदा then, राक्षसशार्दूलम् tiger among Rakshasas, मन्दम् faint tone, वाचम् these words, उदीरयत् revealed.",
      "explanation": "And there after questioned by him (Ravana) Saardula revealed these words overwhelmed by fear, in faint tone to the tiger among Rakshasas.",
      "telugu_translation": "మరియు అక్కడ అతనిని (రావణుడు) ప్రశ్నించగా, సార్దుల భయంతో ముంచెత్తిన ఈ మాటలను రాక్షసులలోని పులికి మందమైన స్వరంతో చెప్పాడు.",
      "comments": ""
    },
    {
      "shloka": 5,
      "shloka_text": "नतेचारयितुंशक्याराजन्वानरपुङ्गवाः । विक्रान्ताबलवन्तश्चराघवेणचरक्षिताः ।।6.30.5।।",
      "transliteration": "",
      "translation": "राजन् O king!, विक्रान्ता valiant, बलवन्तश्च highly powerful, राघवेण by Raghava, रक्षिताःच are protected also, ते with them, वानरपुङ्गवा Vanara heroes, चारयितुम् spy on, नशक्या not possible.",
      "explanation": "\"O King! the Vanara heroes are valiant and highly powerful. They are also protected by Rama. It is not possible to spy on them.\"",
      "telugu_translation": "\"ఓ రాజా! వానర వీరులు పరాక్రమవంతులు మరియు అత్యంత శక్తివంతులు. వారు కూడా రామునిచే రక్షించబడ్డారు. వారిపై గూఢచర్యం చేయడం సాధ్యం కాదు.\"",
      "comments": ""
    },
    {
      "shloka": 6,
      "shloka_text": "नापिसम्भाषितुंशक्यास्सम्प्रश्नोऽत्रनलभ्यते । सर्वतोरक्ष्यतेपन्थावानरैःपर्वतोपमै ।।6.30.6।।",
      "transliteration": "",
      "translation": "सम्भाषितुमपि even to converse, नशक्या not possible, अत्र there, सम्प्रश्न to question, नविद्यते not known, पन्था examine, सर्वत all over, पर्वतोपमै resembling mountains, वानरै Vanaras, रक्ष्यते guarded.",
      "explanation": "\"It is not possible to converse with them or to question and or to examine, since they are guarded all over by mountains like Vanaras.\"",
      "telugu_translation": "\"వానరస్ వంటి పర్వతాలచే రక్షించబడినందున వారితో సంభాషించడం లేదా ప్రశ్నించడం మరియు పరిశీలించడం సాధ్యం కాదు.\"",
      "comments": ""
    },
    {
      "shloka": 7,
      "shloka_text": "प्रविष्टमात्रेज्ञातोऽहंबलेतस्मिन्नचारिते । बलाद्गृहीतोरक्षोभिर्बहुधाऽस्मिविचालितः ।।6.30.7।।",
      "transliteration": "",
      "translation": "तस्मिन् their, बले army, प्रविष्टमात्रे as soon as I entered into, अचारिते was observed, अहम् I, ज्ञात was detected, रक्षोभि even the guards, बलात् forcibly, गृहीत seized, बहुधा many, विचालित rolled on ground, अस्मि me.",
      "explanation": "\"No sooner I entered their army, I was detected. I was forcibly seized by their guards and rolled on the ground.\"",
      "telugu_translation": "\"నేను వారి సైన్యంలోకి ప్రవేశించిన వెంటనే, నేను గుర్తించబడ్డాను. నన్ను వారి గార్డులు బలవంతంగా పట్టుకుని నేలపై పడేశారు.\"",
      "comments": ""
    },
    {
      "shloka": 8,
      "shloka_text": "जानुभिर्मुष्टिभिर्दन्तेस्तलैश्चाभिहतोभृशम् । परिणीतोऽस्मिहरिभिर्बलवद्भिरमर्षणैः ।।6.30.8।।",
      "transliteration": "",
      "translation": "जानुभि with knees, मुष्टिभि with fist, दन्ते with teeth, तलैश्च and even with palms, भृशम् intensely, अभिहत beaten, अमर्षणै indignantly, हरिभि the monkeys, बलवद्भि in the army, परिणीत paraded, आस्मि me.",
      "explanation": "\"The monkeys had beaten me with fists, bitten my palms with teeth, beaten me intensely and paraded me in the army indignantly.\"",
      "telugu_translation": "\"కోతులు నన్ను పిడికిలితో కొట్టాయి, నా అరచేతులను పళ్ళతో కొరికాయి, నన్ను తీవ్రంగా కొట్టాయి మరియు కోపంగా నన్ను సైన్యంలో ఊరేగించాయి.\"",
      "comments": ""
    },
    {
      "shloka": 9,
      "shloka_text": "परिणीयचसर्वत्रनीतोऽहंरामसंसदम् । रुधिरादिग्धसर्वाङ्गोविह्वलश्चलितेन्द्रियः ।।6.30.9।।",
      "transliteration": "",
      "translation": "रुधिरादिग्धसर्वाङ्ग all limbs bleeding, विह्वल lost senses, चलितेन्द्रिय lost control of limbs, अहम् I, सर्वत्रपरिणीय all over paraded, रामसंसदम् to the assembly of Rama, नीत led.",
      "explanation": "\"With all my limbs wet with bleeding, control over senses lost, after parading, I was led to the assembly of Rama.\"",
      "telugu_translation": "\"నా అవయవాలన్నీ రక్తస్రావంతో తడిసి, ఇంద్రియాలపై నియంత్రణ కోల్పోయి, ఊరేగింపు తర్వాత, నన్ను రాముడి సభకు నడిపించారు.\"",
      "comments": ""
    },
    {
      "shloka": 10,
      "shloka_text": "हरिभिर्वध्यमानश्चयाचमानःकृताञ्जलिः । राघवेणपरित्रातोजीवामीतियदृच्छया ।।6.30.10।।",
      "transliteration": "",
      "translation": "हरिभि monkeys also, वध्यमान smitten, कृताञ्जलि offering salutation with folded palms, याचमान pleading, राघवेण from Raghava, परित्रात protection, यदृच्छया by chance, जीवामीति alive.",
      "explanation": "\"While smitten by the monkeys, offering salutation with folded hands, and pleading for protection from Raghava, luckily, I am alive.\"",
      "telugu_translation": "\"కోతుల చేత దెబ్బలు తింటూ, ముకుళిత హస్తాలతో నమస్కరిస్తూ, రాఘవ నుండి రక్షించమని వేడుకుంటున్నప్పుడు, అదృష్టవశాత్తూ నేను బ్రతికే ఉన్నాను.\"",
      "comments": ""
    },
    {
      "shloka": 11,
      "shloka_text": "एषशैलैश्शिलाभिश्चपूरयित्वामहार्णवम् । द्वारमाश्रित्यलङ्कायारामस्तिष्ठतिसायुधः ।।6.30.11।।",
      "transliteration": "",
      "translation": "एष that way, राम Rama, शैलै rocks, शिलाभिश्च and even stones, महावर्णवम् great ocean, पूरयित्वा filled, सायुध equipped with arms, लङ्काया Lanka's, द्वारम् entrance, आश्रित्य taking position, तिष्ठति stands.",
      "explanation": "\"Having filled the great ocean with rocks and stones in that way, taking position at the entrance of Lanka Rama stands equipped with arms.\"",
      "telugu_translation": "\"ఆ విధంగా మహా సముద్రాన్ని రాళ్ళతో, రాళ్ళతో నింపి, లంకా రాముని ప్రవేశ ద్వారం వద్ద ఆయుధాలు ధరించి నిలబడి ఉన్నాడు.\"",
      "comments": ""
    },
    {
      "shloka": 12,
      "shloka_text": "गरुडव्यूहमास्थायसर्वतोहरिभिर्वृतः । मांविसृज्यमहातेजालङ्कामेवाभिवर्तते ।।6.30.12।।",
      "transliteration": "",
      "translation": "महातेजा O glorious one, माम् me, विसृज्य freeing, हरिभि even monkeys, गरुडव्यूहम् in the form of Garuda, आस्थाय forming, पर्वत mountain, वृत surrounded, लङ्कामेव into Lanka, अभिवर्तते is advancing.",
      "explanation": "\"O glorious King! After releasing me, Rama is advancing into Lanka surrounded by mountains like a monkey army in the form of Garuda.\"",
      "telugu_translation": "\"ఓ మహిమాన్విత రాజా! నన్ను విడిచిపెట్టి, రాముడు గరుడ రూపంలో వానర సైన్యంలా పర్వతాలతో చుట్టుముట్టబడిన లంకలోకి దూసుకుపోతున్నాడు.\"",
      "comments": ""
    },
    {
      "shloka": 13,
      "shloka_text": "पुराप्राकारमायातिक्षिप्रमेकतरंकुरु । सीतांवास्मैप्रयच्छाशुयुद्धंवाप्रदीयताम् ।।6.30.13।।",
      "transliteration": "",
      "translation": "प्राकारम् boundary, पुराआयाति before reaching, क्षिप्रम् quickly, एकतरम् one thing, कुरु do, आशु you will, सीतांवा either Sita, प्रयच्छ set out, युद्धंवास्मै good war, प्रदीयताम् to give.",
      "explanation": "\"Before Rama reaches the boundary, the wall, do one thing quickly. Either give away Sita or set out to give a good war.\"",
      "telugu_translation": "\"రాముడు సరిహద్దు, గోడ చేరేలోపు, ఒక పని త్వరగా చెయ్యి. గాని సీతను ఇవ్వు లేదా మంచి యుద్ధం ఇవ్వడానికి బయలుదేరు.\"",
      "comments": ""
    },
    {
      "shloka": 14,
      "shloka_text": "मनसातंतदाप्रेक्ष्यतच्छ्रुत्वाराक्षसाधिपः । शार्दूलंसुमहद्वाक्यमथोवाचसरावणः ।।6.30.14।।",
      "transliteration": "",
      "translation": "राक्षसाधिप Rakshasa king, स that, रावण Ravana, तदा then, तत् that, श्रुत्वा having heard, मनसा in his mind, तत् that, प्रेक्ष्य reviewing, अथ and then, शार्दूलम् Saardula, सुमहत् a good, वाक्यम् statement, उवाच uttered.",
      "explanation": "\"Having heard what has been said by Saardula, Rakshasa king reviewed in his mind and made a good statement before Saardula.\"",
      "telugu_translation": "\"సార్దుల చెప్పినది విని, రాక్షస రాజు తన మనస్సులో సమీక్షించుకుని, సార్దుల ముందు మంచి ప్రకటన చేసాడు.\"",
      "comments": ""
    },
    {
      "shloka": 15,
      "shloka_text": "यदिमांप्रतियुध्येरन्देवगन्धर्वदानवाः । नैवसीतांप्रदास्यामिसर्वलोकभयादपि ।।6.30.15।।",
      "transliteration": "",
      "translation": "यदि even if, देवगन्धर्वदानव Devas Gandharvas, Danavas, मांप्रतियुध्येरन come to wage war with me, सीतां Sita, प्रदास्यामि give away, सर्वलोकभयादपि threat from all worlds, नैव will not.",
      "explanation": "\"Even if Devas, Gandharvas and Danavas come to wage war with me and even if I have threats from all worlds, I will not give away Sita.\"",
      "telugu_translation": "\"దేవతలు, గంధర్వులు మరియు దానవులు నాతో యుద్ధం చేయడానికి వచ్చినా, నాకు అన్ని లోకాల నుండి బెదిరింపులు వచ్చినా, నేను సీతను ఇవ్వను.\"",
      "comments": ""
    },
    {
      "shloka": 16,
      "shloka_text": "एवमुक्त्वामहातेजारावणःपुनरब्रवीत् । चरिताभवतासेनाकेऽत्रशूराःप्लवङ्गमाः ।।6.30.16।।",
      "transliteration": "",
      "translation": "महातेजाः glorious, रावणः Ravana, एवम् in that manner, उक्त्वा having spoken, पुनः again, अब्रवीत् said, भवता by you, सेना army, चरिता went about, अत्र there, शूराः warriors, प्लवङ्गमाः among the monkeys.",
      "explanation": "Glorious Ravana having spoken like that, again said (to Saardula), \"You moved about in the army (camp) there. Tell me who among the monkeys are warriors?\"",
      "telugu_translation": "మహిమాన్వితుడైన రావణుడు అలా మాట్లాడి, మరల (సార్దులతో) అన్నాడు, \"నువ్వు అక్కడ సైన్యంలో (శిబిరం) తిరిగావు. వానరులలో యోధులు ఎవరో చెప్పు?\"",
      "comments": ""
    },
    {
      "shloka": 17,
      "shloka_text": "कीदृशा: किंप्रभा: सौम्यवानरायेदुरासदाः । कस्यपुत्राश्चपौत्राश्चतत्त्वमाख्याहिराक्षस:।। 6.30.17।।",
      "transliteration": "",
      "translation": "राक्षस Rakshasa, सौम्य gentle one, दुरासदा difficult to encounter, ये those, वानरा Vanaras, किम् प्रभा who are the powerful ones?, कीदृशा of what kind कस्य whose, पुत्रा sons (are they?), पौत्राश्च grandsons (are they?), तत् it, त्वम् you, आख्याहि may speak of.",
      "explanation": "\"Gentle Saardula! Of those who are difficult to encounter, what is their description? Who are the powerful ones among them? Whose sons and grandsons, are they? You may speak.\"",
      "telugu_translation": "\"మృదువైన సార్దులా! ఎదుర్కునేందుకు కష్టంగా ఉన్నవారిలో, వారి వర్ణన ఏమిటి? వారిలో శక్తిమంతులు ఎవరు? ఎవరి కొడుకులు మరియు మనవరాళ్ళు? మీరు మాట్లాడవచ్చు.\"",
      "comments": ""
    },
    {
      "shloka": 18,
      "shloka_text": "तथात्रप्रतिपत्स्यामिज्ञात्वातेषांबलाबलम् । अवश्यंबलसङ् ख्यानंकर्तव्यंयुद्धमिच्छताम् ।।6.30.18।।",
      "transliteration": "",
      "translation": "तेषाम् their, बलाबलम् strength and weakness, ज्ञात्वा knowing, अत्र here, तथा likewise, प्रतिपत्स्यामि I would like to know what to do, युद्धम् war, इच्छताम् desiring, सङ् ख्यानम् their numbers, अवश्यम् essential, बल strength, कर्तव्यं it is essential.",
      "explanation": "\"Likewise knowing their strengths and weaknesses from you I wish to know what to do. It is essential to know their numbers and strength before the war.\"",
      "telugu_translation": "\"అలాగే వారి బలాలు మరియు బలహీనతలను మీ నుండి తెలుసుకుని నేను ఏమి చేయాలో తెలుసుకోవాలనుకుంటున్నాను. యుద్ధానికి ముందు వారి సంఖ్య మరియు బలాన్ని తెలుసుకోవడం చాలా అవసరం.\"",
      "comments": ""
    },
    {
      "shloka": 19,
      "shloka_text": "अथैवमुक्तश्शार्दूलोरावणेनोत्तमश्चरः । इदंवचनमारेभेवक्तुंरावणसन्निधौ ।।6.30.19।।",
      "transliteration": "",
      "translation": "अथ and now, रावणेन by Ravana, एवम् that way, उक्त having spoken, उत्तमःचर good spy, शार्दूल Saardula, रावणसन्निधौ in the presence of Ravana, इदम् thus, वचनम् these words, वक्तुम् to tell, आरेभे proceeded.",
      "explanation": "\"When Ravana had spoken that way, good spy Saardula proceeded to tell these words in the presence of Ravana.\"",
      "telugu_translation": "\"రావణుడు అలా మాట్లాడినప్పుడు, మంచి గూఢచారి సార్దుల రావణుని సమక్షంలో ఈ మాటలు చెప్పసాగాడు.\"",
      "comments": ""
    },
    {
      "shloka": 20,
      "shloka_text": "अथर्क्षरजसःपुत्रोयुधिराजासुदुर्जयः । गद्गदस्याथपुत्त्रोऽत्रजाम्बवानितिविश्रुतः ।।6.30.20।।",
      "transliteration": "",
      "translation": "अथ and then, र्क्षरजसः Rksaraja's, पुत्रो son, in war, राजा king, सुदुर्जयः difficult to win over, युधि in war, विश्रुतः widely known, जाम्बवानिति he is known as Jambavan गद्गदस्याथ Gadgada's पुत्त्रोऽत्र son.",
      "explanation": "\"Certainly, king Sugriva, the son of Rksharaja's, is difficult to be conquered in battle. Here is the son of Gadgada, famously called as Jambavan.\"",
      "telugu_translation": "\"ఖచ్చితంగా, ఋక్షరాజు కుమారుడైన రాజు సుగ్రీవుడు యుద్ధంలో జయించడం కష్టం. ఇక్కడ గద్గద కుమారుడు జాంబవాన్ అని పిలుస్తారు.\"",
      "comments": ""
    },
    {
      "shloka": 21,
      "shloka_text": "गद्गदस्यैवपुत्त्रोऽन्योगुरुपुत्र: शतक्रतोः । कदनंयस्यपुत्रेणकृतमेकेनरक्षसाम् ।।6.30.21।।",
      "transliteration": "",
      "translation": "आन्य another, गद्गदस्यैव Gadgada's, पुत्त्र son, शतक्रतो an epithet of Indra, (known as Dhumra), गुरुपुत्र son of Brhaspati, (Kesari), यस्य his, पुत्रेण by his son Hanuman, एकेन alone, रक्षसाम् Rakshasas, कदनम् killing of many, कृतम् did.",
      "explanation": "Another son of Gadgada is Dhumra. One who killed many Rakshasas is Hanuman, the son of Kesari, who is the son of Brhaspati.",
      "telugu_translation": "గద్గద మరొక కుమారుడు ధూమ్ర. చాలా మంది రాక్షసులను చంపినవాడు బృహస్పతి కొడుకు కేసరి కొడుకు హనుమంతుడు.",
      "comments": ""
    },
    {
      "shloka": 22,
      "shloka_text": "सुषेणश्चापिधर्मात्मापुत्रोधर्मस्यवीर्यवान् । सौम्यस्सोमात्मजश्चात्रराजन् दधिमुखःकपिः ।।6.30.22।।",
      "transliteration": "",
      "translation": "राजन् O king!, धर्मात्म righteous self, पुत्र son, वीर्यवान् a valiant one, धर्मास्य of the Lord of death (Yamadharma), सुषेणश्च Sushena, अत्र here, स्सोमात्मज moon's son, सौम्य noble, कपि Vanara, अत्र here, दधिमुख Dadhimukha.",
      "explanation": "\"O king! Here is a heroic and righteous Sushena, the son of the Lord of death (Yamadharma). Here is Dadhimukha son of noble moon.\"",
      "telugu_translation": "\"ఓ రాజా! ఇదిగో మృత్యుదేవత (యమధర్మ) పుత్రుడు, వీరుడు మరియు నీతిమంతుడైన సుషేనుడు ఉన్నాడు. ఇదిగో చంద్రుని కుమారుడు దధిముఖ.\"",
      "comments": ""
    },
    {
      "shloka": 23,
      "shloka_text": "सुमुखोदुर्मुखश्चात्रवेगदर्शीचवानरः । मृत्युर्वानररूपेणनूनंसृष्टस्स्वयम्भुवा ।।6.30.23।।",
      "transliteration": "",
      "translation": "सुमुख Sumukha, दुर्मुखश्चात्र Durmukha, वेगदर्शीच Vegadarsi, वानर Vanaras, नूनम् surely, स्वयम्भुवा by the selfborn (Lord Brahma), वानररूपेण in Vanara form, सृष्ट created, मृत्यु God of death.",
      "explanation": "\"Vanaras Sumukha, Durmukha and Vegadarsi are surely created by Brahma in the Vanara form of DeathGod.\"",
      "telugu_translation": "\"వానరస్ సుముఖ, దుర్ముఖ మరియు వేగదర్శిని ఖచ్చితంగా బ్రహ్మదేవుని వానర రూపంలో సృష్టించారు.\"",
      "comments": ""
    },
    {
      "shloka": 24,
      "shloka_text": "पुत्त्रोहुतवहस्याथनीलस्सेनापतिस्स्वयम् । अनिलस्यचपुत्त्रोऽत्रहनूमानितिविश्रुतः ।।6.30.24।।",
      "transliteration": "",
      "translation": "हुतवहस्य fire god's, पुत्त्र son, स्वयम् himself, सेनापति army chief, नील Nila, अथ here, हनूमानिति is Hanuman, विश्रुत widely known, अनिलस्यपुत्र son of wind god.",
      "explanation": "\"The firegod's son indeed is the army chief known as Nila, and here is windgod's son widely known as Hanuman.\"",
      "telugu_translation": "\"అగ్నిదేవుని కుమారుడే నీలా అని పిలువబడే సైన్యాధ్యక్షుడు, మరియు ఇక్కడ హనుమంతునిగా ప్రసిద్ధి చెందిన వాయుదేవుని కుమారుడు.\"",
      "comments": ""
    },
    {
      "shloka": 25,
      "shloka_text": "नप्ताशक्रस्यदुर्धर्षोबलवानङ्गदोयुवा । मैन्दश्चद्विविदश्चोभौबलिनावश्विसम्भवौ ।।6.30.25।। पुत्त्रावैवस्वतस्यात्रपञ्चकालान्तकोपमाः । गजोगवाक्षोगवयश्शरभोगन्धमादनः ।।6.30.26।। दशवानरकोट्यश्चशूराणांयुद्धकाङ्क्षिणाम् । श्रीमतांदेवपुत्त्राणांशेषंनाख्यातुमुत्सहे ।।6.30.27।।",
      "transliteration": "",
      "translation": "शक्रस्य Indra's, नप्ता grandson, दुर्धर्ष indomitable, बलवान् powerful, युवा young, अङ्गद Angada, आश्विसम्भवौ twins born of Ashwini, बलिना strong, मैन्दश्च Mainda, द्विविदश्च and Dwivida, उभौ both, अथ now, वैनस्वतस्य Vynaswathasya's (Yama, the Lord of death ), पुत्त्रा sons, कालान्तकोपमा resemble god of death (spirit of time), गज: Gaja, गवाक्ष: Gavaksha, गवय: Gavaya, शरभः Sarabha, गन्धमादनः Gandhamadana, पञ्च five, शूराणाम् heroes, युद्धकाङ्क्षिणाम् desiring to wage war, दश ten, वानरकोट्यश्च crores of Vanaras, श्रीमताम् prosperous, देवपुत्राणाम् sons of gods, शेषम् remaining ones, आख्यातुम् to speak, नउत्सहे not possible.",
      "explanation": "\"The indomitable and powerful young Angada is the grandson of Indra, the strong Mainda and Dwivida are both the twin sons of Ashwini Devas, Gaja, Gavaksha, Gavaya, Sarabha and Gandhamadana are the five sons of Yama, the god of death. There are ten crores of heroic and prosperous Vanaras desiring to wage war who are the sons of gods. It is not possible to speak of the remaining ones\", said Saardula to Ravana.\"",
      "telugu_translation": "\"అత్యంత శక్తివంతుడైన యువకుడు అంగదుడు ఇంద్రుని మనుమడు, బలవంతుడు మైందుడు మరియు ద్వివిదుడు అశ్వినీ దేవతలకు కవల కుమారులు, గజ, గవాక్ష, గవయ, శరభ, గంధమాదనుడు మృత్యుదేవత అయిన యమకు ఐదుగురు కుమారులు. వీరుడు, సంపన్నులైన వానరులకు పదికోట్ల మంది యుద్ధం చేయగలరు. మిగిలినవి\", అన్నాడు శార్దూల రావణుడితో.\"",
      "comments": ""
    },
    {
      "shloka": 26,
      "shloka_text": "नप्ताशक्रस्यदुर्धर्षोबलवानङ्गदोयुवा । मैन्दश्चद्विविदश्चोभौबलिनावश्विसम्भवौ ।।6.30.25।। पुत्त्रावैवस्वतस्यात्रपञ्चकालान्तकोपमाः । गजोगवाक्षोगवयश्शरभोगन्धमादनः ।।6.30.26।। दशवानरकोट्यश्चशूराणांयुद्धकाङ्क्षिणाम् । श्रीमतांदेवपुत्त्राणांशेषंनाख्यातुमुत्सहे ।।6.30.27।।",
      "transliteration": "",
      "translation": "शक्रस्य Indra's, नप्ता grandson, दुर्धर्ष indomitable, बलवान् powerful, युवा young, अङ्गद Angada, आश्विसम्भवौ twins born of Ashwini, बलिना strong, मैन्दश्च Mainda, द्विविदश्च and Dwivida, उभौ both, अथ now, वैनस्वतस्य Vynaswathasya's (Yama, the Lord of death ), पुत्त्रा sons, कालान्तकोपमा resemble god of death (spirit of time), गज: Gaja, गवाक्ष: Gavaksha, गवय: Gavaya, शरभः Sarabha, गन्धमादनः Gandhamadana, पञ्च five, शूराणाम् heroes, युद्धकाङ्क्षिणाम् desiring to wage war, दश ten, वानरकोट्यश्च crores of Vanaras, श्रीमताम् prosperous, देवपुत्राणाम् sons of gods, शेषम् remaining ones, आख्यातुम् to speak, नउत्सहे not possible.",
      "explanation": "\"The indomitable and powerful young Angada is the grandson of Indra, the strong Mainda and Dwivida are both the twin sons of Ashwini Devas, Gaja, Gavaksha, Gavaya, Sarabha and Gandhamadana are the five sons of Yama, the god of death. There are ten crores of heroic and prosperous Vanaras desiring to wage war who are the sons of gods. It is not possible to speak of the remaining ones\", said Saardula to Ravana.\"",
      "telugu_translation": "\"అత్యంత శక్తివంతుడైన యువకుడు అంగదుడు ఇంద్రుని మనుమడు, బలవంతుడు మైందుడు మరియు ద్వివిదుడు అశ్వినీ దేవతలకు కవల కుమారులు, గజ, గవాక్ష, గవయ, శరభ, గంధమాదనుడు మృత్యుదేవత అయిన యమకు ఐదుగురు కుమారులు. వీరుడు, సంపన్నులైన వానరులకు పదికోట్ల మంది యుద్ధం చేయగలరు. మిగిలినవి\", అన్నాడు శార్దూల రావణుడితో.\"",
      "comments": ""
    },
    {
      "shloka": 27,
      "shloka_text": "नप्ताशक्रस्यदुर्धर्षोबलवानङ्गदोयुवा । मैन्दश्चद्विविदश्चोभौबलिनावश्विसम्भवौ ।।6.30.25।। पुत्त्रावैवस्वतस्यात्रपञ्चकालान्तकोपमाः । गजोगवाक्षोगवयश्शरभोगन्धमादनः ।।6.30.26।। दशवानरकोट्यश्चशूराणांयुद्धकाङ्क्षिणाम् । श्रीमतांदेवपुत्त्राणांशेषंनाख्यातुमुत्सहे ।।6.30.27।।",
      "transliteration": "",
      "translation": "शक्रस्य Indra's, नप्ता grandson, दुर्धर्ष indomitable, बलवान् powerful, युवा young, अङ्गद Angada, आश्विसम्भवौ twins born of Ashwini, बलिना strong, मैन्दश्च Mainda, द्विविदश्च and Dwivida, उभौ both, अथ now, वैनस्वतस्य Vynaswathasya's (Yama, the Lord of death ), पुत्त्रा sons, कालान्तकोपमा resemble god of death (spirit of time), गज: Gaja, गवाक्ष: Gavaksha, गवय: Gavaya, शरभः Sarabha, गन्धमादनः Gandhamadana, पञ्च five, शूराणाम् heroes, युद्धकाङ्क्षिणाम् desiring to wage war, दश ten, वानरकोट्यश्च crores of Vanaras, श्रीमताम् prosperous, देवपुत्राणाम् sons of gods, शेषम् remaining ones, आख्यातुम् to speak, नउत्सहे not possible.",
      "explanation": "\"The indomitable and powerful young Angada is the grandson of Indra, the strong Mainda and Dwivida are both the twin sons of Ashwini Devas, Gaja, Gavaksha, Gavaya, Sarabha and Gandhamadana are the five sons of Yama, the god of death. There are ten crores of heroic and prosperous Vanaras desiring to wage war who are the sons of gods. It is not possible to speak of the remaining ones\", said Saardula to Ravana.\"",
      "telugu_translation": "\"అధికారిక మరియు శక్తివంతమైన యువ అంగదుడు ఇంద్రుని మనవడు, బలమైన మైంద మరియు ద్వివిద ఇద్దరూ అశ్వినీ దేవతల కవల కుమారులు, గజ, గవాక్ష, గవయ, శరభ మరియు గంధమాదనుడు మృత్యుదేవత అయిన యమ యొక్క ఐదుగురు కుమారులు. దేవతల పుత్రులైన పదికోట్ల మంది వీర, సంపన్నులైన వానరులు యుద్ధం చేయాలనుకుంటున్నారు. మిగిలిన వాటి గురించి మాట్లాడటం కుదరదు\" అని రావణుడితో చెప్పాడు శార్దూల.",
      "comments": ""
    },
    {
      "shloka": 28,
      "shloka_text": "पुत्त्रोदशरथस्यैषसिंहसंहनोयुवा । दूषणोनिहतोयेनखरश्चत्रिशिरास्तथा ।।6.30.28।।",
      "transliteration": "",
      "translation": "सिंहसंहनन built like lion in form, एष that, युवा young one, दशरथस्य Dasaratha's, पुत्त्र son, त्रिशिरा Trisira.",
      "explanation": "\"That young one whose build is like a lion is Dasaratha's son who slayed Dushana, even Khara, like wise Trisira.\"",
      "telugu_translation": "\"సింహం వంటి నిర్మాణం ఉన్న ఆ యువకుడు త్రిశిర వంటి దూషణను, ఖరుడిని కూడా వధించిన దశరథ పుత్రుడు.\"",
      "comments": ""
    },
    {
      "shloka": 29,
      "shloka_text": "नास्तिरामस्यसदृशोविक्रमेभुविकश्चन । विराधोनिहतोयेनकबन्धश्चान्तकोपमः ।।6.30.29।।",
      "transliteration": "",
      "translation": "येन by whom, विराध Viradha, निहत was killed, अन्तकोपम one like Lord of death, कबन्धश्च even Kabhanda, रामस्य Rama's, विक्रमे by valour, सदृश equal, कश्चन perhaps, भूवि in this world, नास्ति not.",
      "explanation": "\"Viradha and even Kabhanda who was like the Lord of death were killed by Rama. Perhaps there is none equal to Rama in valour in this world.\"",
      "telugu_translation": "\"విరాధ, మృత్యుదేవత లాంటి కభాండను కూడా రాముడు చంపేశాడు. బహుశా ఈ లోకంలో పరాక్రమంలో రాముడికి సాటి ఎవరూ లేరేమో.\"",
      "comments": ""
    },
    {
      "shloka": 30,
      "shloka_text": "वक्तुंनशक्तोरामस्यनरःकश्चिद्गुणान् क्षितौ । जनस्थानगतायेनयावन्तोराक्षसाहताः ।।6.30.30।।",
      "transliteration": "",
      "translation": "येन by whom, जनस्थानगता approaching Janasthana, यावन्त all, राक्षसा Rakshasas, हता were killed, रामस्य by Rama, गुणान् virtues, वक्तुम् to speak of, नर human, कश्चित् even, क्षितौ to recount, नशक्त not possible.",
      "explanation": "\"It is not even possible to recount the virtues of Rama who killed all the Rakshasas approaching Janasthana.\"",
      "telugu_translation": "\"జనస్థానానికి చేరువవుతున్న రాక్షసులందరినీ సంహరించిన రాముడి పుణ్యాన్ని చెప్పుకోవడం కూడా సాధ్యం కాదు.\"",
      "comments": ""
    },
    {
      "shloka": 31,
      "shloka_text": "लक्ष्मणश्चात्रधर्मात्मामातङ्गानामिवर्षभः । यस्यबाणपथंप्राप्यनजीवेदपिवासवः ।।6.30.31।।",
      "transliteration": "",
      "translation": "यस्य his, बाणपथम् within the range of arrows, प्राप्य strike, वासवःअपि even Indra, नजीवेत् not be alive, धर्मात्मा righteous, मातङ्गानाम् proud elephant, ऋषभःइव like a bull, लक्ष्मणश्च Lakshmana's, अत्र here.",
      "explanation": "\"Here is righteous Lakshmana, who is like a bull (foremost) resembling a proud elephant. Even Indra will not be alive with in the range of his arrows when he strikes.\"",
      "telugu_translation": "\"ఇదిగో నీతిమంతుడైన లక్ష్మణుడు, గర్వించే ఏనుగును పోలిన ఎద్దు (ముఖ్యమైన) వంటివాడు. ఇంద్రుడు కూడా అతని బాణాల పరిధిలో సజీవంగా ఉండడు.\"",
      "comments": ""
    },
    {
      "shloka": 32,
      "shloka_text": "श्वेतोज्योतिर्मुखश्चात्रभास्करस्यात्मसम्भवौ । वरुणस्यचपुत्त्रोऽन्योःहेमकूटःप्लवङ्गमः ।।6.30.32।। विश्वकर्मसुतोवीरोनलःप्लवगसत्तमः । विक्रान्तोबलवानत्रवसुपुत्रस्सदुर्धरः ।।6.30.33।।",
      "transliteration": "",
      "translation": "भास्करस्य Sun god's, आत्मसम्भवौ sprung from Sun god, श्वेत Swetha, ज्योतिर्मुखश्च Jyothirmukha, वरुणस्य Varuna's, अन्यःपुत्त्र other son, हेमकूट Hemakuta, प्लवङ्गम monkey, विश्वकर्मसुत son of Vishwakarma, वीर heroes, प्लवगसत्तम foremost among the monkeys, नल Nala, विक्रान्त valiant, बलवान् gallant, वसुपुत्र son of Vasu, विक्रान्त valiant, वेगवान् swift in action, वसुपुत्त्र son of Vasu, स he, दुर्धर is Durdhara, अत्र here.",
      "explanation": "\"Here are Swetha and Jyothirmukha sons of Sun god Hemakuta another son of Varuna Nala the foremost among the monkey heroes is the valiant son of Vishwakarma and Durdhara of swift action, the son of Vasu.\"",
      "telugu_translation": "\"ఇక్కడ సూర్య దేవుడు హేమకూట శ్వేత మరియు జ్యోతిర్ముఖ కుమారులు ఉన్నారు, వరుణ నల యొక్క మరొక కుమారుడు వానర వీరులలో అగ్రగణ్యుడు విశ్వకర్మ మరియు దుర్ధర యొక్క పరాక్రమ పుత్రుడు, వసు పుత్రుడు.\"",
      "comments": ""
    },
    {
      "shloka": 33,
      "shloka_text": "श्वेतोज्योतिर्मुखश्चात्रभास्करस्यात्मसम्भवौ । वरुणस्यचपुत्त्रोऽन्योःहेमकूटःप्लवङ्गमः ।।6.30.32।। विश्वकर्मसुतोवीरोनलःप्लवगसत्तमः । विक्रान्तोबलवानत्रवसुपुत्रस्सदुर्धरः ।।6.30.33।।",
      "transliteration": "",
      "translation": "भास्करस्य Sun god's, आत्मसम्भवौ sprung from Sun god, श्वेत Swetha, ज्योतिर्मुखश्च Jyothirmukha, वरुणस्य Varuna's, अन्यःपुत्त्र other son, हेमकूट Hemakuta, प्लवङ्गम monkey, विश्वकर्मसुत son of Vishwakarma, वीर heroes, प्लवगसत्तम foremost among the monkeys, नल Nala, विक्रान्त valiant, बलवान् gallant, वसुपुत्र son of Vasu, विक्रान्त valiant, वेगवान् swift in action, वसुपुत्त्र son of Vasu, स he, दुर्धर is Durdhara, अत्र here.",
      "explanation": "\"Here are Swetha and Jyothirmukha sons of Sun god Hemakuta another son of Varuna Nala the foremost among the monkey heroes is the valiant son of Vishwakarma and Durdhara of swift action, the son of Vasu.\"",
      "telugu_translation": "\"ఇక్కడ సూర్య దేవుడు హేమకూట శ్వేత మరియు జ్యోతిర్ముఖ కుమారులు ఉన్నారు, వరుణ నల యొక్క మరొక కుమారుడు వానర వీరులలో అగ్రగణ్యుడు విశ్వకర్మ మరియు దుర్ధర యొక్క పరాక్రమ పుత్రుడు, వసు పుత్రుడు.\"",
      "comments": ""
    },
    {
      "shloka": 34,
      "shloka_text": "राक्षसानांवरिष्ठश्चतवभ्रातावीभीषणः । प्रतिगृह्यपुरींलङ्कांराघवस्यहितेरतः ।।6.30.34।।",
      "transliteration": "",
      "translation": "राक्षसानाम् of the Rakshasas, वरिष्ठश्च jewel, तव your, भ्राता brother, विभीषण Vibheeshana, राघवस्य Raghava's, हिते wellwisher, रत remains, लङ्कापुरीम् city of Lanka, प्रतिगृह्य received.",
      "explanation": "\"Here is your brother Vibheeshana the jewel among Rakshasas, who remains as a wellwisher of Rama and has received the city of Lanka (to whom Rama has offered Lanka).\"",
      "telugu_translation": "\"ఇదిగో మీ సోదరుడు విభీషణుడు రాక్షసులలో రత్నం, అతను రాముని శ్రేయోభిలాషిగా మిగిలి ఉన్నాడు మరియు లంకా నగరాన్ని (రాముడు లంకాను సమర్పించాడు) పొందాడు.\"",
      "comments": ""
    },
    {
      "shloka": 35,
      "shloka_text": "इतिसर्वंसमाख्यातंतवेदंवानरंबलम् । सुवेलेऽधिष्ठितंशैलेशेषकार्येभवान्गतिः ।।6.30.35।।",
      "transliteration": "",
      "translation": "इति this, सुवेलेशैले on Suvela mountain, अधिष्ठितम् stationed, इदम् thus, सर्वम् everything, वानरंबलम् Vanara strength, तवइदं to you this, समाख्यातम् described, शेषकार्ये rest of the task, भवान् your, गति decide.",
      "explanation": "\"I have described to you everything about the Vanara strength stationed on Suvela mountain. You may decide the rest of the task to be done.\" ।। इत्यार्षेवाल्मीकीयेश्रीमद्रामायणेआदिकाव्येयुद्धकाण्डेत्रिंशस्सर्गः ।। This is the end of the thirtieth sarga of Yuddha Kanda of the first epic the holy Ramayana composed by sage Valmiki.",
      "telugu_translation": "\"సువేళ పర్వతం మీద ఉన్న వానర బలం గురించి నేను మీకు అన్నీ వివరించాను. మిగిలిన పనిని మీరు నిర్ణయించుకోవచ్చు.\" .. ఇత్యార్షేవాల్మీకీయశ్రీమద్రామాయణేఆదికావ్యేయుద్ధకణ్డేత్రింశస్సర్గః । ఇది వాల్మీకి మహర్షిచే రచించబడిన పవిత్ర రామాయణం యొక్క మొదటి ఇతిహాసం యొక్క యుద్ధ కాండ యొక్క ముప్పైవ సర్గ ముగింపు.",
      "comments": ""
    }
  ]
}