{
  "kanda": "Uttara Kanda",
  "kanda_slug": "uttara-kanda",
  "sarga": 48,
  "shloka_count": 27,
  "shlokas": [
    {
      "shloka": 1,
      "shloka_text": "लक्ष्मणस्य वचः श्रुत्वा दारुणं जनकात्मजा । परं विषादमागम्य वैदेही निपपात ह ।। 7.48.1 ।।",
      "transliteration": "lakṣmaṇasya vacaḥ śrutvā dāruṇaṃ janakātmajā | paraṃ viṣādamāgamya vaidehī nipapāta ha || 7.48.1 ||",
      "translation": "",
      "explanation": "",
      "telugu_translation": "జనకుని కుమార్తె లక్ష్మణుని భయంకరమైన మాటలు విన్నది కానీ వైదేహి నిరాశతో కుంగిపోయింది",
      "comments": ""
    },
    {
      "shloka": 2,
      "shloka_text": "सा मुहूर्तमिवासञ्ज्ञा बाष्पपर्याकुलेक्षणा । लक्ष्मणं दीनया वाचा उवाच जनकात्मजा ।। 7.48.2 ।।",
      "transliteration": "sā muhūrtamivāsañjñā bāṣpaparyākulekṣaṇā | lakṣmaṇaṃ dīnayā vācā uvāca janakātmajā || 7.48.2 ||",
      "translation": "",
      "explanation": "",
      "telugu_translation": "ఆమె ఒక్క క్షణం స్పృహ కోల్పోయినట్లు అనిపించింది, ఆమె కళ్ళు నీళ్లతో నిండిపోయాయి. జనకుని కుమార్తె లక్ష్మణునితో సౌమ్య స్వరంతో ఇలా చెప్పింది",
      "comments": ""
    },
    {
      "shloka": 3,
      "shloka_text": "मामिकेयं तनुर्नूनं सृष्टा दुःखाय लक्ष्मण । धात्रा यस्यास्तथा मे ऽद्य दुःखमूर्तिः प्रदृश्यते ।। 7.48.3 ।।",
      "transliteration": "māmikeyaṃ tanurnūnaṃ sṛṣṭā duḥkhāya lakṣmaṇa | dhātrā yasyāstathā me 'dya duḥkhamūrtiḥ pradṛśyate || 7.48.3 ||",
      "translation": "",
      "explanation": "",
      "telugu_translation": "ఓ లక్ష్మణా నా ఈ దేహం నీ బాధల కోసం సృష్టించబడి ఉండాలి ఈ రోజు నేను ఆ తల్లిలాంటి బాధను చూస్తున్నాను.",
      "comments": ""
    },
    {
      "shloka": 4,
      "shloka_text": "किं नु पापं कृतं पूर्वं को वा दारैर्वियोजितः । या ऽहं शुद्धसमाचारा त्यक्ता नृपतिना सती ।। 7.48.4 ।।",
      "transliteration": "kiṃ nu pāpaṃ kṛtaṃ pūrvaṃ ko vā dārairviyojitaḥ | yā 'haṃ śuddhasamācārā tyaktā nṛpatinā satī || 7.48.4 ||",
      "translation": "",
      "explanation": "",
      "telugu_translation": "ఇంతకుముందు ఏం పాపం చేసాడు, భార్యను విడిచిపెట్టింది ఎవరు? నేను రాజుచే విడిచిపెట్టబడిన పవిత్ర స్త్రీని",
      "comments": ""
    },
    {
      "shloka": 5,
      "shloka_text": "पुरा ऽहमाश्रमे वासं रामपादानुवर्तिनी । अनुरुध्यापि सौमित्रे दुःखे च परिवर्तिनी ।। 7.48.5 ।।",
      "transliteration": "purā 'hamāśrame vāsaṃ rāmapādānuvartinī | anurudhyāpi saumitre duḥkhe ca parivartinī || 7.48.5 ||",
      "translation": "",
      "explanation": "",
      "telugu_translation": "గతంలో నేను ఆశ్రమంలో నివసించాను మరియు రామచంద్ర భగవానుడి అడుగుజాడలను అనుసరించాను. ఆమె అడ్డుపడినా లక్ష్మణుడు దుఃఖంతో తిరుగుతున్నాడు",
      "comments": ""
    },
    {
      "shloka": 6,
      "shloka_text": "सा कथं ह्याश्रमे सौम्य वत्स्यामि विजनीकृता । आख्यास्यामि च कस्याहं दुःखं दुःखपरायणा ।। 7.48.6 ।।",
      "transliteration": "sā kathaṃ hyāśrame saumya vatsyāmi vijanīkṛtā | ākhyāsyāmi ca kasyāhaṃ duḥkhaṃ duḥkhaparāyaṇā || 7.48.6 ||",
      "translation": "",
      "explanation": "",
      "telugu_translation": "ఓ సౌమ్యుడు, నేను ఎడారిగా ఉన్నప్పుడు ఆ ఆశ్రమంలో ఎలా జీవించగలను? మరియు నేను ఎవరి బాధను దుఃఖానికి అంకితం చేశానో చెబుతాను",
      "comments": ""
    },
    {
      "shloka": 7,
      "shloka_text": "किं नु वक्ष्यामि मुनिषु कर्म वा सत्कृतं च किम् । कस्मिंश्चित् कारणे त्यक्ता राघवेण महात्मना ।। 7.48.7 ।।",
      "transliteration": "kiṃ nu vakṣyāmi muniṣu karma vā satkṛtaṃ ca kim | kasmiṃścit kāraṇe tyaktā rāghaveṇa mahātmanā || 7.48.7 ||",
      "translation": "",
      "explanation": "",
      "telugu_translation": "ఋషుల గురించి నేనేం చెప్పగలను, లేదా ఏది సరైనది? కొన్ని కారణాల వల్ల ఆమెను రాముడు వదిలిపెట్టాడు",
      "comments": ""
    },
    {
      "shloka": 8,
      "shloka_text": "न खल्वद्यैव सौमित्रे जीवितं जाह्नवीजले । त्यजेयं राजवंशस्तु भर्तुर्मे परिहास्यते ।। 7.48.8 ।।",
      "transliteration": "na khalvadyaiva saumitre jīvitaṃ jāhnavījale | tyajeyaṃ rājavaṃśastu bharturme parihāsyate || 7.48.8 ||",
      "translation": "",
      "explanation": "",
      "telugu_translation": "ఈ రోజు కాదు, ఓ లక్ష్మణా, జాహ్నవి నీటిలో జీవం ఉంది. నేను రాజ వంశాన్ని వదులుకుంటాను కాని నా భర్త అపహాస్యం పాలవుతాడు",
      "comments": ""
    },
    {
      "shloka": 9,
      "shloka_text": "यथाज्ञं कुरु सोमित्रे त्यज मां दुःखभागिनीम् । निदेशे स्थीयतां राज्ञः शृणु चेदं वचो मम ।। 7.48.9 ।।",
      "transliteration": "yathājñaṃ kuru somitre tyaja māṃ duḥkhabhāginīm | nideśe sthīyatāṃ rājñaḥ śṛṇu cedaṃ vaco mama || 7.48.9 ||",
      "translation": "",
      "explanation": "",
      "telugu_translation": "నీవు ఆజ్ఞాపించినట్లు చేయు సోమిత్రా, బాధలో ఉన్న నన్ను విడిచిపెట్టు. రాజు ఆజ్ఞను అనుసరించి నా మాటలు వినండి",
      "comments": ""
    },
    {
      "shloka": 10,
      "shloka_text": "श्वश्रूणामविशेषेण प्राञ्जलिप्रग्रहेण च । शिरसा ऽ ऽवन्द्य चरणौ कुशलं ब्रूहि पार्थिवम् ।। 7.48.10 ।।",
      "transliteration": "śvaśrūṇāmaviśeṣeṇa prāñjalipragraheṇa ca | śirasā ' 'vandya caraṇau kuśalaṃ brūhi pārthivam || 7.48.10 ||",
      "translation": "",
      "explanation": "",
      "telugu_translation": "అత్తగారిని కూడా తేడా లేకుండా ముకుళిత హస్తాలతో పలకరించాడు. అతని పాదాలకు తల వంచి, మీరు ఎలా ఉన్నారో రాజుకు చెప్పండి",
      "comments": ""
    },
    {
      "shloka": 11,
      "shloka_text": "शिरसा ऽभिनतो ब्रूयाः सर्वासामेव लक्ष्मण । वक्तव्यश्चापि नृपतिर्धर्मेषु सुसमाहितः ।। 7.48.11 ।।",
      "transliteration": "śirasā 'bhinato brūyāḥ sarvāsāmeva lakṣmaṇa | vaktavyaścāpi nṛpatirdharmeṣu susamāhitaḥ || 7.48.11 ||",
      "translation": "",
      "explanation": "",
      "telugu_translation": "తల వంచి వాళ్లందరికీ చెప్పు లక్ష్మణ్. రాజుకు ధర్మం బాగా తెలుసు అని చెప్పాలి",
      "comments": ""
    },
    {
      "shloka": 12,
      "shloka_text": "जानासि च यथा शुद्धा सीता तत्त्वेन राघव । भक्त्या च परया युक्ता हिता च तव नित्यशः ।। 7.48.12 ।।",
      "transliteration": "jānāsi ca yathā śuddhā sītā tattvena rāghava | bhaktyā ca parayā yuktā hitā ca tava nityaśaḥ || 7.48.12 ||",
      "translation": "",
      "explanation": "",
      "telugu_translation": "ఓ రామా, సీత ఎంత పవిత్రంగా ఉంటుందో నీకు తెలుసు. ఆమె ఎల్లప్పుడూ అత్యున్నత భక్తిని కలిగి ఉంటుంది మరియు మీకు మంచిది",
      "comments": ""
    },
    {
      "shloka": 13,
      "shloka_text": "अहं त्यक्ता त्वया वीर अयशोभीरुणा जने । यच्च ते वचनीयं स्यादपवादसमुत्थितम् । मया च परिहर्तव्यं त्वं हि मे परमा गतिः ।। 7.48.13 ।।",
      "transliteration": "ahaṃ tyaktā tvayā vīra ayaśobhīruṇā jane | yacca te vacanīyaṃ syādapavādasamutthitam | mayā ca parihartavyaṃ tvaṃ hi me paramā gatiḥ || 7.48.13 ||",
      "translation": "",
      "explanation": "",
      "telugu_translation": "ఓ పరాక్రమవంతుడా, నా కీర్తికి భయపడి నన్ను విడిచిపెట్టావు. మరియు మీరు చెప్పేది ఏదైనా, మినహాయింపు ద్వారా పెంచబడింది. మరియు మీరు నా అంతిమ ఆశ్రయం కాబట్టి నేను దానిని నివారించాలి",
      "comments": ""
    },
    {
      "shloka": 14,
      "shloka_text": "वक्तव्यश्चेति नृपतिर्धमेण सुसमाहितः । यथा भ्रातृषु वर्तेथास्तथा पौरेषु नित्यदा ।। 7.48.14 ।।",
      "transliteration": "vaktavyaśceti nṛpatirdhameṇa susamāhitaḥ | yathā bhrātṛṣu vartethāstathā paureṣu nityadā || 7.48.14 ||",
      "translation": "",
      "explanation": "",
      "telugu_translation": "ఏం చేయాలో రాజు చాలా జాగ్రత్తగా చెప్పాడు. మీరు మీ సోదరులతో ఎలా ప్రవర్తించాలో అలాగే మీరు ఎల్లప్పుడూ మీ పౌరులతో వ్యవహరించాలి",
      "comments": ""
    },
    {
      "shloka": 15,
      "shloka_text": "परमो ह्येष धर्मस्ते तस्मात्कीर्तिरनुत्तमा ।। 7.48.15 ।।",
      "transliteration": "paramo hyeṣa dharmaste tasmātkīrtiranuttamā || 7.48.15 ||",
      "translation": "",
      "explanation": "",
      "telugu_translation": "ఇది మీ సర్వోన్నతమైన కర్తవ్యం కాబట్టి మీ కీర్తి ఎనలేనిది",
      "comments": ""
    },
    {
      "shloka": 16,
      "shloka_text": "यत्तु पौरजनो राजन्धर्मेण समवाप्नुयात् । अहं तु नानुशोचामि स्वशरीरं नरर्षभ ।। 7.48.16 ।।",
      "transliteration": "yattu paurajano rājandharmeṇa samavāpnuyāt | ahaṃ tu nānuśocāmi svaśarīraṃ nararṣabha || 7.48.16 ||",
      "translation": "",
      "explanation": "",
      "telugu_translation": "ఓ రాజా, నగరంలోని పౌరులు మతపరమైన సూత్రాల ద్వారా ఏది పొందినా సరే, ఓ ఉత్తమ పురుషులా, నా శరీరం గురించి నేను చింతించను.",
      "comments": ""
    },
    {
      "shloka": 17,
      "shloka_text": "यथापवादं पौराणां तथैव रघुनन्दन । पतिर्हि देवता नार्याः पतिर्बन्धुः पतिर्गुरुः ।। 7.48.17 ।।",
      "transliteration": "yathāpavādaṃ paurāṇāṃ tathaiva raghunandana | patirhi devatā nāryāḥ patirbandhuḥ patirguruḥ || 7.48.17 ||",
      "translation": "",
      "explanation": "",
      "telugu_translation": "ఓ రఘు వంశస్థుడా, పౌరుల విషయంలోనూ ఇదే నిజం స్త్రీకి భర్త దేవుడు, భర్త స్నేహితుడు, భర్త గురువు",
      "comments": ""
    },
    {
      "shloka": 18,
      "shloka_text": "प्राणैरपि प्रियं तस्माद्भर्तुः कार्यं विशेषतः । इति मद्वचनाद्रामो वक्तव्यो मम सङ्ग्रहः । निरीक्ष्य मा ऽद्य गच्छ त्वमृतुकालातिवर्तिनीम् ।। 7.48.18 ।।",
      "transliteration": "prāṇairapi priyaṃ tasmādbhartuḥ kāryaṃ viśeṣataḥ | iti madvacanādrāmo vaktavyo mama saṅgrahaḥ | nirīkṣya mā 'dya gaccha tvamṛtukālātivartinīm || 7.48.18 ||",
      "translation": "",
      "explanation": "",
      "telugu_translation": "ఇది ఒకరి జీవితానికి కూడా ప్రియమైనది, అందువల్ల ఒకరి భర్త యొక్క విధి చాలా ముఖ్యమైనది. రాముడు నా మాటల్లో చెప్పాల్సిన సంకలనం ఇది. నన్ను చూసి ఈరోజు వెళ్ళకు, నీకు మరణకాలం దాటిపోయింది",
      "comments": ""
    },
    {
      "shloka": 19,
      "shloka_text": "एवं ब्रुवन्त्यां सीतायां लक्ष्मणो दीनचेतनः । शिरसा ऽ ऽवन्द्य धरणीं व्याहर्तुं न शशाक ह ।। 7.48.19 ।।",
      "transliteration": "evaṃ bruvantyāṃ sītāyāṃ lakṣmaṇo dīnacetanaḥ | śirasā ' 'vandya dharaṇīṃ vyāhartuṃ na śaśāka ha || 7.48.19 ||",
      "translation": "",
      "explanation": "",
      "telugu_translation": "సీత ఇలా మాట్లాడుతుండగా లక్ష్మణుడు నిరుత్సాహానికి గురై నేలకి తల వంచి మాట్లాడలేకపోయాడు.",
      "comments": ""
    },
    {
      "shloka": 20,
      "shloka_text": "प्रदक्षिणं च तां कृत्वा रुदन्नेव महास्वनः । ध्यात्वा मुहूर्तं तामाह किं मां वक्ष्यसि शोभने ।। 7.48.20 ।।",
      "transliteration": "pradakṣiṇaṃ ca tāṃ kṛtvā rudanneva mahāsvanaḥ | dhyātvā muhūrtaṃ tāmāha kiṃ māṃ vakṣyasi śobhane || 7.48.20 ||",
      "translation": "",
      "explanation": "",
      "telugu_translation": "అతను ఆమెకు ప్రదక్షిణలు చేసి పెద్దగా ఏడవడం ప్రారంభించాడు. అతను ఒక్క క్షణం ఆలోచించి, ఆమెతో అన్నాడు, \"ఓ సుందరి నువ్వు నాకు ఏమి చెబుతావు",
      "comments": ""
    },
    {
      "shloka": 21,
      "shloka_text": "दृष्टपूर्वं न ते रूपं पादौ दृष्टौ तवानघे । कथमत्र हि पश्यामि रामेण रहितां वने ।। 7.48.21 ।।",
      "transliteration": "dṛṣṭapūrvaṃ na te rūpaṃ pādau dṛṣṭau tavānaghe | kathamatra hi paśyāmi rāmeṇa rahitāṃ vane || 7.48.21 ||",
      "translation": "",
      "explanation": "",
      "telugu_translation": "నేనెప్పుడూ నీ రూపాన్ని చూడలేదు, ఓ పాపరహితుడా, నీ పాదాలను చూశాను. రాముడు లేని ఆమెను ఇక్కడ అడవిలో ఎలా చూడగలను",
      "comments": ""
    },
    {
      "shloka": 22,
      "shloka_text": "इत्युक्त्वा तां नमस्कृत्य पुनर्नावमुपारुहत् । आरुह्य च पुनर्नावं नाविकं चाभ्यचोदयत् ।। 7.48.22 ।।",
      "transliteration": "ityuktvā tāṃ namaskṛtya punarnāvamupāruhat | āruhya ca punarnāvaṃ nāvikaṃ cābhyacodayat || 7.48.22 ||",
      "translation": "",
      "explanation": "",
      "telugu_translation": "ఇలా చెప్పి ఆమెకు నమస్కరించి తిరిగి పడవ ఎక్కాడు. అతను తిరిగి పడవ ఎక్కి నావికుడిని కోరాడు",
      "comments": ""
    },
    {
      "shloka": 23,
      "shloka_text": "स गत्वा चोत्तरं तीरं शोकभारसमन्वितः । सम्मूढ इव दुःखेन रथमध्यारुहद्द्रुतम् ।। 7.48.23 ।।",
      "transliteration": "sa gatvā cottaraṃ tīraṃ śokabhārasamanvitaḥ | sammūḍha iva duḥkhena rathamadhyāruhaddrutam || 7.48.23 ||",
      "translation": "",
      "explanation": "",
      "telugu_translation": "అతను దుఃఖంతో ఉత్తర తీరానికి వెళ్ళాడు. దుఃఖంతో దిక్కుతోచనివాడిలా తొందరగా రథం ఎక్కాడు",
      "comments": ""
    },
    {
      "shloka": 24,
      "shloka_text": "मुहुर्मुहुः परावृत्य दृष्ट्वा सीतामनाथवत् । चेष्टन्तीं परतीरस्थां लक्ष्मणः प्रययावथ ।। 7.48.24 ।।",
      "transliteration": "muhurmuhuḥ parāvṛtya dṛṣṭvā sītāmanāthavat | ceṣṭantīṃ paratīrasthāṃ lakṣmaṇaḥ prayayāvatha || 7.48.24 ||",
      "translation": "",
      "explanation": "",
      "telugu_translation": "అతను మళ్ళీ మళ్ళీ వెనక్కి తిరిగి, సీతను అనాథలా చూసాడు, ఆమె అటువైపు కదులుతూ ఉండగా లక్ష్మణుడు ఆమెను అనుసరించాడు.",
      "comments": ""
    },
    {
      "shloka": 25,
      "shloka_text": "दूरस्थं रथमालोक्य लक्ष्मणं च मुहूर्मुहुः । निरीक्षमाणां तूद्विग्नां सीतां शोकः समाविशत् ।। 7.48.25 ।।",
      "transliteration": "dūrasthaṃ rathamālokya lakṣmaṇaṃ ca muhūrmuhuḥ | nirīkṣamāṇāṃ tūdvignāṃ sītāṃ śokaḥ samāviśat || 7.48.25 ||",
      "translation": "",
      "explanation": "",
      "telugu_translation": "మళ్లీ మళ్లీ రథం వైపు చూడగా, దూరంగా లక్ష్మణుడు ఆందోళనగా చూస్తున్న సీతను దుఃఖం ముంచెత్తింది.",
      "comments": ""
    },
    {
      "shloka": 26,
      "shloka_text": "सा दुःखभारावनता यशस्विनी यशोधना नाथमपश्यती सती । रुरोद सा बर्हिणनादिते वने महास्वनं दुःखपरायणा सती ।। 7.48.26 ।।",
      "transliteration": "sā duḥkhabhārāvanatā yaśasvinī yaśodhanā nāthamapaśyatī satī | ruroda sā barhiṇanādite vane mahāsvanaṃ duḥkhaparāyaṇā satī || 7.48.26 ||",
      "translation": "",
      "explanation": "",
      "telugu_translation": "దుఃఖంతో ఉక్కిరిబిక్కిరైన ప్రతిష్ట మరియు పవిత్రమైన స్త్రీ తన యజమానిని కనుగొనలేకపోయింది. ఆ నిర్మల స్త్రీ నెమళ్ల శబ్దానికి అడవిలో బిగ్గరగా కేకలు వేసింది",
      "comments": ""
    },
    {
      "shloka": 27,
      "shloka_text": "इत्यार्षे श्रीमद्रामायणे वाल्मीकीये आदिकाव्ये श्रीमदुत्तरकाण्डे ऽष्टचत्वारिंशः सर्गः ।। 48 ।।",
      "transliteration": "ityārṣe śrīmadrāmāyaṇe vālmīkīye ādikāvye śrīmaduttarakāṇḍe 'ṣṭacatvāriṃśaḥ sargaḥ || 48 ||",
      "translation": "",
      "explanation": "",
      "telugu_translation": "ఇది శ్రీమద్-రామాయణంలోని నలభై ఎనిమిదవ శ్లోకం, వాల్మీకి మూల కావ్యం, శ్రీమద్-ఉత్తరకాండలో. 48..",
      "comments": ""
    }
  ]
}