{
  "kanda": "Ayodhya Kanda",
  "kanda_slug": "ayodhya-kanda",
  "sarga": 99,
  "shloka_count": 42,
  "shlokas": [
    {
      "shloka": 1,
      "shloka_text": "निविष्टायां तु सेनायामुत्सुको भरतस्तदा। जगाम भ्रातरं द्रष्टुं शत्रुघ्नमनुदर्शयन्।।2.99.1।।",
      "transliteration": "",
      "translation": "तदा then, सेनायाम् when the army, निविष्टायाम्  encamped, भरतः Bharata, उत्सुकः with eagerness, शत्रुघ्नम् Satrughna, अनुदर्शयन् showing, भ्रातरम् brother, द्रष्टुम् to see, जगाम went.",
      "explanation": "Eager to see his brother, Bharata encamped the army and set out showing the hermitage to Satrughna.",
      "telugu_translation": "తన సోదరుడిని చూడాలనే ఆత్రుతతో భరతుడు సైన్యాన్ని విడిచిపెట్టి శతృఘ్నుడికి ఆశ్రమాన్ని చూపిస్తూ బయలుదేరాడు.",
      "comments": "Bharata sees Rama seated in the hermitage with matted hair and bark robes with Sita nearby -- Bharata's lamentation."
    },
    {
      "shloka": 2,
      "shloka_text": "ऋषिं वसिष्ठं सन्दिश्य मातृ़र्मे शीघ्रमानय। इति त्वरितमग्रे स जगाम गुरुवत्सलः।।2.99.2।।",
      "transliteration": "",
      "translation": "गुरुवत्सलः devoted towards elders, सः Bharata, मे my, मातृ़ः mothers, शीघ्रम् quickly, आनय bring, इति thus, ऋषिम् rishi, वसिष्ठम् Vasistha, सन्दिश्य having conveyed, त्वरितम् quickly, अग्रे ahead, जगाम proceeded.",
      "explanation": "Bharata, deeply devoted towards elders, indicated to sage Vasistha to bring along the mothers, and  proceeded ahead quickly.",
      "telugu_translation": "పెద్దల పట్ల అమితమైన భక్తి ఉన్న భరతుడు, తల్లులను వెంట తీసుకురావాలని వశిష్ట మహర్షికి సూచించి, వేగంగా ముందుకు సాగాడు.",
      "comments": ""
    },
    {
      "shloka": 3,
      "shloka_text": "सुमन्त्रस्त्वपि शत्रुघ्नमदूरादन्वपद्यत। रामदर्शनजस्तर्षो भरतस्येव तस्य च।।2.99.3।।",
      "transliteration": "",
      "translation": "सुमन्त्रस्त्वपि Sumantra on his part, शत्रुघ्नम् to Satrughna, अदूरात् not far from, अन्वपद्यत  followed, रामदर्शनजः arising from seeing Rama, तर्षः overeager, तस्य च for him also, भरतस्येव is like that of Bharata.",
      "explanation": "Sumantra, who was overeager, like Bharata, to see Rama, followed Satrughna who was not far from him.",
      "telugu_translation": "రాముని చూడాలని భరతుని వలె అత్యుత్సాహంతో ఉన్న సుమంత్రుడు తనకు దూరంగా ఉన్న శతృఘ్నుడిని అనుసరించాడు.",
      "comments": ""
    },
    {
      "shloka": 4,
      "shloka_text": "गच्छन्नेवाथ भरतस्तापसालय संस्थिताम्। भ्रातुः पर्णकुटीं श्रीमानुटजं च ददर्श ह।। 2.99.4।।",
      "transliteration": "",
      "translation": "अथ thereafter, श्रीमान् the majestic one, भरतः Bharata, गच्छन्नेव while walking, तापसालयसंस्थिताम् situated like huts of hermits, भ्रातुः brother's, पर्णकुटीम् hut made of leaves, उटजं च thatched cottage, ददर्श ह beheld.",
      "explanation": "While walking, Bharata beheld a hut made of leaves looking like a hermit's cottage.",
      "telugu_translation": "నడుస్తూ ఉండగా, భరతుడు సన్యాసి కుటీరంలా కనిపించే ఆకులతో చేసిన ఒక గుడిసెను చూశాడు.",
      "comments": ""
    },
    {
      "shloka": 5,
      "shloka_text": "शालायास्त्वग्रत स्तस्या ददर्श भरत स्तदा। काष्ठानि चावभग्नानि पुष्पाण्युपचितानि च।।2.99.5।।",
      "transliteration": "",
      "translation": "तदा then, भरतः Bharata, तस्याः शालायाः that leafy hut's, अग्रतः in front of, अवभग्नानि shattered, काष्ठानि logs of wood, उपचितानि plucked, पुष्पाणि च also flowers, ददर्श beheld.",
      "explanation": "In front of that hut Bharata beheld shattered logs of wood and also flowers plucked.",
      "telugu_translation": "ఆ గుడిసె ముందు భరతుడు పగిలిపోయిన చెక్క దుంగలు, పూలు తెంపడం చూశాడు.",
      "comments": ""
    },
    {
      "shloka": 6,
      "shloka_text": "स लक्ष्मणस्य रामस्य ददर्शाऽश्रममीयुषः। कृतं वृक्षेष्वभिज्ञानं कुशचीरैः क्वचित्क्वचित्।।2.99.6।।",
      "transliteration": "",
      "translation": "सः he, आश्रमम् hermitage, ईयुषः of a man proceeding towards, लक्ष्मणस्य Lakshmana's, रामस्य Rama's, क्वचित् क्वचित् here and there, वृक्षेषु on trees, कुशचीरैः with kusa grass and strips of bark, कृतम् rendered, अभिज्ञानम् as a sign to ascertain, ददर्श beheld.",
      "explanation": "Bharata beheld here and there knots of kusa grass and strips of bark tied on trees as signs to ascertain the way to the hermitage of Rama and Lakshmana.",
      "telugu_translation": "రామ, లక్ష్మణుల ఆశ్రమానికి మార్గాన్ని నిర్ధారించడానికి గుర్తుగా చెట్లపై కట్టిన కుశ గడ్డి మరియు బెరడు స్ట్రిప్స్‌ను భరతుడు అక్కడక్కడ చూశాడు.",
      "comments": ""
    },
    {
      "shloka": 7,
      "shloka_text": "ददर्श वने तस्मिन्महत स्सञ्चयान्कृतान्। मृगाणां महिषाणां च करीषै शशीतकारणात्।।2.99.7।।",
      "transliteration": "",
      "translation": "सः that Bharata, तस्मिन् वने in that forest, शीतकारणात् due to cold, मृगाणाम् deer's, महिषाणां च also of buffaloes, करीषैः dried cakes of dung, कृतान् prepared, महतः large, सञ्चयान् heaps, ददर्श beheld.",
      "explanation": "He also beheld large heaps of dried cakes of dung of buffaloes and deer for use against cold in the forest.",
      "telugu_translation": "అతను అడవిలో చలికి వ్యతిరేకంగా ఉపయోగించే గేదెలు మరియు జింకల పేడతో ఎండబెట్టిన పెద్ద కుప్పలను కూడా చూశాడు.",
      "comments": ""
    },
    {
      "shloka": 8,
      "shloka_text": "गच्छन्नेव महाबाहुर्द्युतिमान्भरत स्तदा। शत्रुघ्नं चाब्रवीद्धृष्टस्तानमात्यांश्च सर्वशः।।2.99.8।।",
      "transliteration": "",
      "translation": "महाबाहुः longarmed, द्युतिमान् effulgent, भरतः Bharata, तदा then, गच्छन्नेव while going, हृष्टः rejoiced, शत्रुघ्नं च to Satrughna, सर्वशः all around, तान् those, अमात्यांश्च to the ministers, अब्रवीत् said.",
      "explanation": "Walking on, the longarmed, effulgent and delighted Bharata said to Satrughna and the ministers surrounding him:",
      "telugu_translation": "నడుస్తూ, పొడవాటి, ప్రకాశవంతంగా మరియు సంతోషించిన భరతుడు శత్రుఘ్నుడితో మరియు అతని చుట్టూ ఉన్న మంత్రులతో ఇలా అన్నాడు:",
      "comments": ""
    },
    {
      "shloka": 9,
      "shloka_text": "मन्ये प्राप्ताः स्म तं देशं भरद्वाजो यमब्रवीत्। नातिदूरे हि मन्येऽहं नदीं मन्दाकिनीमितः।।2.99.9।।",
      "transliteration": "",
      "translation": "यम् about which, भरद्वाजः Bharadwaja, अब्रवीत् had spoken, तं देशम् that region, प्राप्ताः स्म  we must have reached, मन्ये I think, मन्दाकिनीं नदीं Mandakini river, इतः from here, नातिदूरे not far, अहम् I, मन्ये think.",
      "explanation": "We must have reached the region about which Bharadwaja had spoken. I think river Mandakini is not far from here.",
      "telugu_translation": "భరద్వాజుడు చెప్పిన ప్రాంతానికి మనం చేరుకోవాలి. మందాకిని నది ఇక్కడికి చాలా దూరంలో లేదని నా అభిప్రాయం.",
      "comments": ""
    },
    {
      "shloka": 10,
      "shloka_text": "उच्चैर्बद्धानि चीराणि लक्ष्मणेन भवेदयम्। अभिज्ञानकृतः पन्था अकाले गन्तुमिच्छता।।2.99.10।।",
      "transliteration": "",
      "translation": "चीराणि long bark garments, उच्चैः on lofty places (trees), बद्धानि have been fastened, अयम् this, अकाले at odd times, गन्तुम् to move out, इच्छता wishing, लक्ष्मणेन by Lakshmana, अभिज्ञानकृतः marks of identification, पन्थाः भवेत् it must have been the path.",
      "explanation": "Here are long bark garments fastened on lofty places as marks of identification left by Lakshmana, to locate the path at odd times which may be needed while going out.",
      "telugu_translation": "ఇక్కడ లక్ష్మణుడు విడిచిపెట్టిన గుర్తింపు చిహ్నాలుగా ఎత్తైన ప్రదేశాలలో బిగించిన పొడవాటి బెరడు వస్త్రాలు ఉన్నాయి, బయటికి వెళ్లేటప్పుడు అవసరమైన బేసి సమయాల్లో మార్గాన్ని గుర్తించడానికి.",
      "comments": ""
    },
    {
      "shloka": 11,
      "shloka_text": "इदं चोदात्तदन्तानां कुञ्जराणां तरस्विनाम्। शैलपार्श्वे परिक्रान्तमन्योन्यमभिगर्जताम्।।2.99.11।।",
      "transliteration": "",
      "translation": "शैलपार्श्वे on the hillside, इदम् this, उदात्तदन्तानाम् of the largetusked, तरस्विनाम् swift अन्योन्यम् charging at one another, अभिगर्जताम् trumpeting, कुञ्जराणाम् elephants', परिक्रान्तम् place.",
      "explanation": "This must be the place on the hillside on which mighty tuskers wander about trumpeting and charging at one another.",
      "telugu_translation": "బలమైన ఏనుగులు ఒకదానికొకటి బాకా ఊదుతూ, వత్తిడి చేస్తూ సంచరించే కొండపైన ఉండే ప్రదేశం ఇది.",
      "comments": ""
    },
    {
      "shloka": 12,
      "shloka_text": "यमेवाधातुमिच्छन्ति तापसा स्सततं वने। तस्यासौ दृश्यते धूम स्सङ्कुलः कृष्णवर्त्मनः।।2.99.12।।",
      "transliteration": "",
      "translation": "वने in the forest, तापसाः ascetics, सततम् always, यमेव only whom, आधातुम् to maintain, इच्छन्ति wishing, तस्य that, कृष्णवर्त्मनः of blacktrailed fires, असौ this, सङ्कुलः thick, धूमः smoke, दृश्यते is seen.",
      "explanation": "Here is the thick smoke emanating from the blacktrailed fire maintained perpetually by the ascetics living in the forest.",
      "telugu_translation": "అడవిలో నివసించే తపస్విలచే నిత్యం నిర్వహించబడుతున్న నల్లటి మంటల నుండి దట్టమైన పొగ వెలువడుతోంది.",
      "comments": ""
    },
    {
      "shloka": 13,
      "shloka_text": "अत्राहं पुरुषव्याघ्रं गुरुसत्कारकारिणम्। आर्यं द्रक्ष्यामि संहृष्टो महर्षिमिव राघवम्।।2.99.13।।",
      "transliteration": "",
      "translation": "अहम् I, पुरुषव्याघ्रम् the best of men, Rama, गुरुसत्कारकारिणम् rendering great hospitality, आर्यम् venerable, महर्षिमिव like a great sage, राघवम् to Rama, संहृष्टः with a delighted heart, अत्र here, द्रक्ष्यामि I shall see.",
      "explanation": "I shall see here with a delighted heart the venerable Rama, the best of men, who renders great hospitality (to elders) and who resembles a maharshi.",
      "telugu_translation": "గొప్ప ఆతిథ్యం (పెద్దలకు) అందించే మరియు మహర్షిని పోలి ఉండే మనుష్యులలో ఉత్తముడైన పూజ్యుడైన రాముడిని నేను సంతోషకరమైన హృదయంతో ఇక్కడ చూస్తాను.",
      "comments": ""
    },
    {
      "shloka": 14,
      "shloka_text": "अथ गत्वा मुहूर्तन्तु चित्रकूटं स राघवः। मन्दाकिनीमनुप्राप्तस्तं जनं चेदमब्रवीत्।।2.99.14।।",
      "transliteration": "",
      "translation": "अथ thereafter, सः राघवः that Bharata, चित्रकूटम् towards Chitrakuta (mountain), मुहूर्तम् for a moment, गत्वा having gone, मन्दाकिनीम् river Mandakini, अनुप्राप्तः having reached, तं जनम्  to those people, इदम् those words, अब्रवीत् said.",
      "explanation": "Bharata walked for a short distance towards mount Chitrkuta when he reached river Mandakini. And then said to his ministers:",
      "telugu_translation": "భరతుడు మందాకిని నదికి చేరుకున్నప్పుడు చిత్రకూట పర్వతం వైపు కొద్ది దూరం నడిచాడు. ఆపై తన మంత్రులతో ఇలా అన్నాడు:",
      "comments": ""
    },
    {
      "shloka": 15,
      "shloka_text": "जगत्यां पुरषव्याघ्र आस्ते वीरासने रतः। जनेन्द्रो निर्जनं प्राप्य धिङ्मे जन्म सजीवितम्।।2.99.15।।",
      "transliteration": "",
      "translation": "जनेन्द्रः the lord of men, पुरषव्याघ्रः a tiger among men, निर्जनम् a place devoid of people, प्राप्य having reached, वीरासने in 'heroic' posture, रतः remaining, जगत्याम् on the ground, आस्ते is sitting, मे my, सजीवितम् life, जन्म birth, धिक् fie upon.",
      "explanation": "Rama, the lord of men, a tiger among men, is sitting on the ground in a 'heroic' (yogic) posture in this secluded forest. O fie upon my birth and my life",
      "telugu_translation": "రాముడు, మనుష్యుల ప్రభువు, మనుషులలో పులి, ఈ ఏకాంత అడవిలో 'వీరోచిత' (యోగి) భంగిమలో నేలపై కూర్చున్నాడు. నా పుట్టుక మరియు నా జీవితం మీద ఓ ఫీ",
      "comments": ""
    },
    {
      "shloka": 16,
      "shloka_text": "मत्कृते व्यसनं प्राप्तो लोकनाथो महाद्युतिः। सर्वान्कामान्परित्यज्य वने वसति राघवः।।2.99.16।।",
      "transliteration": "",
      "translation": "लोकनाथः lord of the world, महाद्युतिः effulgent, राघवः Rama, मत्कृते on my account, व्यसनम्  calamity, प्राप्त: has faced, सर्वान् all, कामान् desires, परित्यज्य renouncing, वने in the forest, वसति is living.",
      "explanation": "Effulgent Rama, the lord of the world, had to renounce all desires and undergo this calamity of living in the forest on my account.",
      "telugu_translation": "జగత్తుకు ప్రభువైన ప్రకాశవంతుడైన రాముడు కోరికలన్నింటినీ త్యజించి నా ఖాతాలో అడవిలో నివసించే ఈ విపత్తును అనుభవించవలసి వచ్చింది.",
      "comments": ""
    },
    {
      "shloka": 17,
      "shloka_text": "इति लोकसमाक्रुष्टः पादेष्वद्य प्रसादयन्। रामस्य निपतिष्यामि सीताया लक्ष्मणस्य च।।2.99.17।।",
      "transliteration": "",
      "translation": "इति thus, लोकसमाक्रुष्टः reviled by the world, अद्य now, प्रसादयन् seeking the grace, रामस्य Rama's, सीतायाः Sita's, लक्ष्मणस्य च and Lakshmana's, पादेषु at the feet, निपतिष्यामि shall fall down.",
      "explanation": "Reviled by the world, I shall now fall at the feet of Sita, Rama and Lakshmana seeking their grace.",
      "telugu_translation": "లోకంచే దూషించబడిన నేను ఇప్పుడు సీత, రామ మరియు లక్ష్మణుల అనుగ్రహం కోసం వారి పాదాలపై పడతాను.",
      "comments": ""
    },
    {
      "shloka": 18,
      "shloka_text": "एवं संविलपं स्तस्मिन्वने दशरथात्मजः। ददर्श महतीं पुण्यां पर्णशालां मनोरमाम्।।2.99.18।। सालतालाश्वकर्णानां पर्णैर्बहुभिरावृताम्। विशालां मृदुभिस्तीर्णां कुशैर्वेदिमिवाध्वरे।।2.99.19।। शक्रायुधनिकाशैश्च कार्मुकैर्भारसाधनैः। रुक्मपृष्ठैर्महासारै श्शोभितां शत्रुबाधकैः।।2.99.20।। अर्क रश्मि प्रतीकाशैर्घोरैस्तूणीगतैश्शरैः। शोभितां दीप्तवदनै स्सर्पैर्भोगवतीमिव।।2.99.21।। महारजतवासोभ्यामसिभ्यां च विराजिताम्। रुक्मबिन्दुविचित्राभ्यां चर्मभ्यां चापि शोभिताम्।।2.99.22।। गोधाङ्गुळित्रैरासक्तैश्चित्रैः काञ्चनभूषितैः। अरिसंघैरनाधृष्यां मृगै स्सिंहगुहा मिव।।2.99.23।।",
      "transliteration": "",
      "translation": "एवम् in that way, संविलपन् lamenting, दशरथात्मजः son of Dasaratha (Bharata), तस्मिन् वने in that forest, महतीम् great, पुण्याम् sacred, मनोरमाम् enchanting, सालतालाश्वकर्णानाम् of sala, palmyra and aswakarna trees, बहुभिः by abundance of, मृदुभिः by soft, पर्णैः with leaves, आवृताम् covered, अध्वरे in the sacrifice, कुशैः with kusa grass, तीर्णाम् spread over, विशालाम् spacious, वेदिमिव like altar, शक्रायुधनिकाशैः resembling the thunderbolt of Indra, भारसाधनैः capable of achieving targets, रुक्मपृष्ठैः goldplated, महासारै: by powerful, शत्रुबाधकैः oppressing the enemies, कार्मुकैः with bows, शोभिताम् glittering, सर्पैः with serpents, भोगवतीम् इव like Bhogavati, अर्करश्मिप्रतीकाशैः like the rays of the Sun, घोरैः by dreadful, दीप्तवदनैः with tips blazing, तूणीगतैः stored in quivers, शरैः with arrows, शोभिताम् adorned with, महारजतवासोभ्याम् scabbards made of silver, असिभ्याम् with a pair of swords, विराजिताम् was shining, रुक्मबिन्दुविचित्राभ्याम् of different colours with golden spots, चर्मभ्याम् with shields, ताम् all of them, काञ्चनभूषितैः decorated with gold, चित्रैः different kinds, आसक्तै: hung, गोधाङ्गुलित्रैः fingerguards made of skin of iguana, मृगैः with the deer, सिंहगुहामिव like the cave of a lion, अरिसङ्घै: with hordes of enemies, अनाधृष्याम् impregnable, पर्णशालाम् hut made of leave, तस्मिन् वने in that forest, ददर्श saw.",
      "explanation": "Lamenting in this way Bharata beheld in that forest an excellent, sacred and enchanting hut covered with a lot of leaves of sala, palmyra and aswakarna trees like a sacrificial altar spread with soft kusa grass. Goldplated bows that resembled the thunderbolt of Indra, powerful and capable of achieving great targets and oppressing the enemies, adorned the hut. Arrows glittering like the rays of the Sun, were dreadful, with blazing heads and stored in quivers adorned it like the hooded serpents illumining the city of Bhogavati (in the nether world). A pair of swords in scabbards made of excellent silver, two shields of different colours with golden spots, fingerguards made of skin of iguana decorated with gold were hanging there. It was impregnable to enemy hordes like the cave of a lion to the deer.",
      "telugu_translation": "ఈ విధంగా విలపిస్తూ భరతుడు ఆ అడవిలో మెత్తని కుశ గడ్డితో వ్యాపించిన యజ్ఞ పీఠం వంటి సాల, తాళపత్ర, అశ్వకర్ణ వృక్షాలతో కప్పబడిన అద్భుతమైన, పవిత్రమైన, మంత్రముగ్ధమైన గుడిసెను చూశాడు. ఇంద్రుని పిడుగును పోలిన బంగారు పూత పూసిన విల్లులు, శక్తివంతమైనవి మరియు గొప్ప లక్ష్యాలను సాధించగల మరియు శత్రువులను అణచివేయగల సామర్థ్యం గలవి, గుడిసెను అలంకరించాయి. సూర్యుని కిరణాల వలె మెరుస్తున్న బాణాలు భయంకరమైనవి, మండుతున్న తలలతో మరియు వణుకులలో భద్రపరచబడి, భోగవతి నగరాన్ని (నెదర్ ప్రపంచంలో) ప్రకాశింపజేసే హుడ్డ్ సర్పాల వలె దానిని అలంకరించాయి. అద్భుతమైన వెండితో చేసిన స్కబార్డ్స్‌లో ఒక జత కత్తులు, బంగారు మచ్చలు కలిగిన వివిధ రంగుల రెండు కవచాలు, బంగారంతో అలంకరించబడిన ఇగువానా చర్మంతో చేసిన ఫింగర్‌గార్డ్‌లు అక్కడ వేలాడుతున్నాయి. అది జింకలకు సింహం గుహలా శత్రు సమూహాలకు అభేద్యమైనది.",
      "comments": ""
    },
    {
      "shloka": 19,
      "shloka_text": "एवं संविलपं स्तस्मिन्वने दशरथात्मजः। ददर्श महातीं पुण्यां पर्णशालां मनोरमाम्।।2.99.18।। सालतालाश्वकर्णानां पर्णैर्बहुभिरावृताम्। विशालां मृदुभिस्तीर्णां कुशैर्वेदिमिवाध्वरे।।2.99.19।। शक्रायुधनिकाशैश्च कार्मुकैर्भारसाधनैः। रुक्मपृष्ठैर्महासारै श्शोभितां शत्रुबाधकैः।।2.99.20।। अर्क रश्मि प्रतीकाशैर्घोरैस्तूणीगतैश्शरैः। शोभितां दीप्तवदनै स्सर्पैर्भोगवतीमिव।।2.99.21।। महारजतवासोभ्यामसिभ्यां च विराजिताम्। रुक्मबिन्दुविचित्राभ्यां चर्मभ्यां चापि शोभिताम्।।2.99.22।। गोधाङ्गुळित्रैरासक्तैश्चित्रैः काञ्चनभूषितैः। अरिसंघैरनाधृष्यां मृगै स्सिंहगुहा मिव।।2.99.23।।",
      "transliteration": "",
      "translation": "एवम् in that way, संविलपन् lamenting, दशरथात्मजः son of Dasaratha (Bharata), तस्मिन् वने in that forest, महतीम् great, पुण्याम् sacred, मनोरमाम् enchanting, सालतालाश्वकर्णानाम् of sala, palmyra and aswakarna trees, बहुभिः by abundance of, मृदुभिः by soft, पर्णैः with leaves, आवृताम् covered, अध्वरे in the sacrifice, कुशैः with kusa grass, तीर्णाम् spread over, विशालाम् spacious, वेदिमिव like altar, शक्रायुधनिकाशैः resembling the thunderbolt of Indra, भारसाधनैः capable of achieving targets, रुक्मपृष्ठैः goldplated, महासारै: by powerful, शत्रुबाधकैः oppressing the enemies, कार्मुकैः with bows, शोभिताम् glittering, सर्पैः with serpents, भोगवतीम् इव like Bhogavati, अर्करश्मिप्रतीकाशैः like the rays of the Sun, घोरैः by dreadful, दीप्तवदनैः with tips blazing, तूणीगतैः stored in quivers, शरैः with arrows, शोभिताम् adorned with, महारजतवासोभ्याम् scabbards made of silver, असिभ्याम् with a pair of swords, विराजिताम् was shining, रुक्मबिन्दुविचित्राभ्याम् of different colours with golden spots, चर्मभ्याम् with shields, ताम् all of them, काञ्चनभूषितैः decorated with gold, चित्रैः different kinds, आसक्तै: hung, गोधाङ्गुलित्रैः fingerguards made of skin of iguana, मृगैः with the deer, सिंहगुहामिव like the cave of a lion, अरिसङ्घै: with hordes of enemies, अनाधृष्याम् impregnable, पर्णशालाम् hut made of leave, तस्मिन् वने in that forest, ददर्श saw.",
      "explanation": "Lamenting in this way Bharata beheld in that forest an excellent, sacred and enchanting hut covered with a lot of leaves of sala, palmyra and aswakarna trees like a sacrificial altar spread with soft kusa grass. Goldplated bows that resembled the thunderbolt of Indra, powerful and capable of achieving great targets and oppressing the enemies, adorned the hut. Arrows glittering like the rays of the Sun, were dreadful, with blazing heads and stored in quivers adorned it like the hooded serpents illumining the city of Bhogavati (in the nether world). A pair of swords in scabbards made of excellent silver, two shields of different colours with golden spots, fingerguards made of skin of iguana decorated with gold were hanging there. It was impregnable to enemy hordes like the cave of a lion to the deer.",
      "telugu_translation": "ఈ విధంగా విలపిస్తూ భరతుడు ఆ అడవిలో మెత్తని కుశ గడ్డితో వ్యాపించిన యజ్ఞ పీఠం వంటి సాల, తాళపత్ర, అశ్వకర్ణ వృక్షాలతో కప్పబడిన అద్భుతమైన, పవిత్రమైన, మంత్రముగ్ధమైన గుడిసెను చూశాడు. ఇంద్రుని పిడుగును పోలిన బంగారు పూత పూసిన విల్లులు, శక్తివంతమైనవి మరియు గొప్ప లక్ష్యాలను సాధించగల మరియు శత్రువులను అణచివేయగల సామర్థ్యం గలవి, గుడిసెను అలంకరించాయి. సూర్యుని కిరణాల వలె మెరుస్తున్న బాణాలు భయంకరమైనవి, మండుతున్న తలలతో మరియు వణుకులలో భద్రపరచబడి, భోగవతి నగరాన్ని (నెదర్ ప్రపంచంలో) ప్రకాశింపజేసే హుడ్డ్ సర్పాల వలె దానిని అలంకరించాయి. అద్భుతమైన వెండితో చేసిన స్కబార్డ్స్‌లో ఒక జత కత్తులు, బంగారు మచ్చలు కలిగిన వివిధ రంగుల రెండు కవచాలు, బంగారంతో అలంకరించబడిన ఇగువానా చర్మంతో చేసిన ఫింగర్‌గార్డ్‌లు అక్కడ వేలాడుతున్నాయి. అది జింకలకు సింహం గుహలా శత్రు సమూహాలకు అభేద్యమైనది.",
      "comments": ""
    },
    {
      "shloka": 20,
      "shloka_text": "एवं संविलपं स्तस्मिन्वने दशरथात्मजः। ददर्श महातीं पुण्यां पर्णशालां मनोरमाम्।।2.99.18।। सालतालाश्वकर्णानां पर्णैर्बहुभिरावृताम्। विशालां मृदुभिस्तीर्णां कुशैर्वेदिमिवाध्वरे।।2.99.19।। शक्रायुधनिकाशैश्च कार्मुकैर्भारसाधनैः। रुक्मपृष्ठैर्महासारै श्शोभितां शत्रुबाधकैः।।2.99.20।। अर्क रश्मि प्रतीकाशैर्घोरैस्तूणीगतैश्शरैः। शोभितां दीप्तवदनै स्सर्पैर्भोगवतीमिव।।2.99.21।। महारजतवासोभ्यामसिभ्यां च विराजिताम्। रुक्मबिन्दुविचित्राभ्यां चर्मभ्यां चापि शोभिताम्।।2.99.22।। गोधाङ्गुळित्रैरासक्तैश्चित्रैः काञ्चनभूषितैः। अरिसंघैरनाधृष्यां मृगै स्सिंहगुहा मिव।।2.99.23।।",
      "transliteration": "",
      "translation": "एवम् in that way, संविलपन् lamenting, दशरथात्मजः son of Dasaratha (Bharata), तस्मिन् वने in that forest, महतीम् great, पुण्याम् sacred, मनोरमाम् enchanting, सालतालाश्वकर्णानाम् of sala, palmyra and aswakarna trees, बहुभिः by abundance of, मृदुभिः by soft, पर्णैः with leaves, आवृताम् covered, अध्वरे in the sacrifice, कुशैः with kusa grass, तीर्णाम् spread over, विशालाम् spacious, वेदिमिव like altar, शक्रायुधनिकाशैः resembling the thunderbolt of Indra, भारसाधनैः capable of achieving targets, रुक्मपृष्ठैः goldplated, महासारै: by powerful, शत्रुबाधकैः oppressing the enemies, कार्मुकैः with bows, शोभिताम् glittering, सर्पैः with serpents, भोगवतीम् इव like Bhogavati, अर्करश्मिप्रतीकाशैः like the rays of the Sun, घोरैः by dreadful, दीप्तवदनैः with tips blazing, तूणीगतैः stored in quivers, शरैः with arrows, शोभिताम् adorned with, महारजतवासोभ्याम् scabbards made of silver, असिभ्याम् with a pair of swords, विराजिताम् was shining, रुक्मबिन्दुविचित्राभ्याम् of different colours with golden spots, चर्मभ्याम् with shields, ताम् all of them, काञ्चनभूषितैः decorated with gold, चित्रैः different kinds, आसक्तै: hung, गोधाङ्गुलित्रैः fingerguards made of skin of iguana, मृगैः with the deer, सिंहगुहामिव like the cave of a lion, अरिसङ्घै: with hordes of enemies, अनाधृष्याम् impregnable, पर्णशालाम् hut made of leave, तस्मिन् वने in that forest, ददर्श saw.",
      "explanation": "Lamenting in this way Bharata beheld in that forest an excellent, sacred and enchanting hut covered with a lot of leaves of sala, palmyra and aswakarna trees like a sacrificial altar spread with soft kusa grass. Goldplated bows that resembled the thunderbolt of Indra, powerful and capable of achieving great targets and oppressing the enemies, adorned the hut. Arrows glittering like the rays of the Sun, were dreadful, with blazing heads and stored in quivers adorned it like the hooded serpents illumining the city of Bhogavati (in the nether world). A pair of swords in scabbards made of excellent silver, two shields of different colours with golden spots, fingerguards made of skin of iguana decorated with gold were hanging there. It was impregnable to enemy hordes like the cave of a lion to the deer.",
      "telugu_translation": "ఈ విధంగా విలపిస్తూ భరతుడు ఆ అడవిలో మెత్తని కుశ గడ్డితో వ్యాపించిన యజ్ఞ పీఠం వంటి సాల, తాళపత్ర, అశ్వకర్ణ వృక్షాలతో కప్పబడిన అద్భుతమైన, పవిత్రమైన, మంత్రముగ్ధమైన గుడిసెను చూశాడు. ఇంద్రుని పిడుగును పోలిన బంగారు పూత పూసిన విల్లులు, శక్తివంతమైనవి మరియు గొప్ప లక్ష్యాలను సాధించగల మరియు శత్రువులను అణచివేయగల సామర్థ్యం గలవి, గుడిసెను అలంకరించాయి. సూర్యుని కిరణాల వలె మెరుస్తున్న బాణాలు భయంకరమైనవి, మండుతున్న తలలతో మరియు వణుకులలో భద్రపరచబడి, భోగవతి నగరాన్ని (నెదర్ ప్రపంచంలో) ప్రకాశింపజేసే హుడ్డ్ సర్పాల వలె దానిని అలంకరించాయి. అద్భుతమైన వెండితో చేసిన స్కబార్డ్స్‌లో ఒక జత కత్తులు, బంగారు మచ్చలు కలిగిన వివిధ రంగుల రెండు కవచాలు, బంగారంతో అలంకరించబడిన ఇగువానా చర్మంతో చేసిన ఫింగర్‌గార్డ్‌లు అక్కడ వేలాడుతున్నాయి. అది జింకలకు సింహం గుహలా శత్రు సమూహాలకు అభేద్యమైనది.",
      "comments": ""
    },
    {
      "shloka": 21,
      "shloka_text": "एवं संविलपं स्तस्मिन्वने दशरथात्मजः। ददर्श महातीं पुण्यां पर्णशालां मनोरमाम्।।2.99.18।। सालतालाश्वकर्णानां पर्णैर्बहुभिरावृताम्। विशालां मृदुभिस्तीर्णां कुशैर्वेदिमिवाध्वरे।।2.99.19।। शक्रायुधनिकाशैश्च कार्मुकैर्भारसाधनैः। रुक्मपृष्ठैर्महासारै श्शोभितां शत्रुबाधकैः।।2.99.20।। अर्क रश्मि प्रतीकाशैर्घोरैस्तूणीगतैश्शरैः। शोभितां दीप्तवदनै स्सर्पैर्भोगवतीमिव।।2.99.21।। महारजतवासोभ्यामसिभ्यां च विराजिताम्। रुक्मबिन्दुविचित्राभ्यां चर्मभ्यां चापि शोभिताम्।।2.99.22।। गोधाङ्गुळित्रैरासक्तैश्चित्रैः काञ्चनभूषितैः। अरिसंघैरनाधृष्यां मृगै स्सिंहगुहा मिव।।2.99.23।।",
      "transliteration": "",
      "translation": "एवम् in that way, संविलपन् lamenting, दशरथात्मजः son of Dasaratha (Bharata), तस्मिन् वने in that forest, महतीम् great, पुण्याम् sacred, मनोरमाम् enchanting, सालतालाश्वकर्णानाम् of sala, palmyra and aswakarna trees, बहुभिः by abundance of, मृदुभिः by soft, पर्णैः with leaves, आवृताम् covered, अध्वरे in the sacrifice, कुशैः with kusa grass, तीर्णाम् spread over, विशालाम् spacious, वेदिमिव like altar, शक्रायुधनिकाशैः resembling the thunderbolt of Indra, भारसाधनैः capable of achieving targets, रुक्मपृष्ठैः goldplated, महासारै: by powerful, शत्रुबाधकैः oppressing the enemies, कार्मुकैः with bows, शोभिताम् glittering, सर्पैः with serpents, भोगवतीम् इव like Bhogavati, अर्करश्मिप्रतीकाशैः like the rays of the Sun, घोरैः by dreadful, दीप्तवदनैः with tips blazing, तूणीगतैः stored in quivers, शरैः with arrows, शोभिताम् adorned with, महारजतवासोभ्याम् scabbards made of silver, असिभ्याम् with a pair of swords, विराजिताम् was shining, रुक्मबिन्दुविचित्राभ्याम् of different colours with golden spots, चर्मभ्याम् with shields, ताम् all of them, काञ्चनभूषितैः decorated with gold, चित्रैः different kinds, आसक्तै: hung, गोधाङ्गुलित्रैः fingerguards made of skin of iguana, मृगैः with the deer, सिंहगुहामिव like the cave of a lion, अरिसङ्घै: with hordes of enemies, अनाधृष्याम् impregnable, पर्णशालाम् hut made of leave, तस्मिन् वने in that forest, ददर्श saw.",
      "explanation": "Lamenting in this way Bharata beheld in that forest an excellent, sacred and enchanting hut covered with a lot of leaves of sala, palmyra and aswakarna trees like a sacrificial altar spread with soft kusa grass. Goldplated bows that resembled the thunderbolt of Indra, powerful and capable of achieving great targets and oppressing the enemies, adorned the hut. Arrows glittering like the rays of the Sun, were dreadful, with blazing heads and stored in quivers adorned it like the hooded serpents illumining the city of Bhogavati (in the nether world). A pair of swords in scabbards made of excellent silver, two shields of different colours with golden spots, fingerguards made of skin of iguana decorated with gold were hanging there. It was impregnable to enemy hordes like the cave of a lion to the deer.",
      "telugu_translation": "ఈ విధంగా విలపిస్తూ భరతుడు ఆ అడవిలో మెత్తని కుశ గడ్డితో వ్యాపించిన యజ్ఞ పీఠం వంటి సాల, తాళపత్ర, అశ్వకర్ణ వృక్షాలతో కప్పబడిన అద్భుతమైన, పవిత్రమైన, మంత్రముగ్ధమైన గుడిసెను చూశాడు. ఇంద్రుని పిడుగును పోలిన బంగారు పూత పూసిన విల్లులు, శక్తివంతమైనవి మరియు గొప్ప లక్ష్యాలను సాధించగల మరియు శత్రువులను అణచివేయగల సామర్థ్యం గలవి, గుడిసెను అలంకరించాయి. సూర్యుని కిరణాల వలె మెరుస్తున్న బాణాలు భయంకరమైనవి, మండుతున్న తలలతో మరియు వణుకులలో భద్రపరచబడి, భోగవతి నగరాన్ని (నెదర్ ప్రపంచంలో) ప్రకాశింపజేసే హుడ్డ్ సర్పాల వలె దానిని అలంకరించాయి. అద్భుతమైన వెండితో చేసిన స్కబార్డ్స్‌లో ఒక జత కత్తులు, బంగారు మచ్చలు కలిగిన వివిధ రంగుల రెండు కవచాలు, బంగారంతో అలంకరించబడిన ఇగువానా చర్మంతో చేసిన ఫింగర్‌గార్డ్‌లు అక్కడ వేలాడుతున్నాయి. అది జింకలకు సింహం గుహలా శత్రు సమూహాలకు అభేద్యమైనది.",
      "comments": ""
    },
    {
      "shloka": 22,
      "shloka_text": "एवं संविलपं स्तस्मिन्वने दशरथात्मजः। ददर्श महातीं पुण्यां पर्णशालां मनोरमाम्।।2.99.18।। सालतालाश्वकर्णानां पर्णैर्बहुभिरावृताम्। विशालां मृदुभिस्तीर्णां कुशैर्वेदिमिवाध्वरे।।2.99.19।। शक्रायुधनिकाशैश्च कार्मुकैर्भारसाधनैः। रुक्मपृष्ठैर्महासारै श्शोभितां शत्रुबाधकैः।।2.99.20।। अर्क रश्मि प्रतीकाशैर्घोरैस्तूणीगतैश्शरैः। शोभितां दीप्तवदनै स्सर्पैर्भोगवतीमिव।।2.99.21।। महारजतवासोभ्यामसिभ्यां च विराजिताम्। रुक्मबिन्दुविचित्राभ्यां चर्मभ्यां चापि शोभिताम्।।2.99.22।। गोधाङ्गुळित्रैरासक्तैश्चित्रैः काञ्चनभूषितैः। अरिसंघैरनाधृष्यां मृगै स्सिंहगुहा मिव।।2.99.23।।",
      "transliteration": "",
      "translation": "एवम् in that way, संविलपन् lamenting, दशरथात्मजः son of Dasaratha (Bharata), तस्मिन् वने in that forest, महतीम् great, पुण्याम् sacred, मनोरमाम् enchanting, सालतालाश्वकर्णानाम् of sala, palmyra and aswakarna trees, बहुभिः by abundance of, मृदुभिः by soft, पर्णैः with leaves, आवृताम् covered, अध्वरे in the sacrifice, कुशैः with kusa grass, तीर्णाम् spread over, विशालाम् spacious, वेदिमिव like altar, शक्रायुधनिकाशैः resembling the thunderbolt of Indra, भारसाधनैः capable of achieving targets, रुक्मपृष्ठैः goldplated, महासारै: by powerful, शत्रुबाधकैः oppressing the enemies, कार्मुकैः with bows, शोभिताम् glittering, सर्पैः with serpents, भोगवतीम् इव like Bhogavati, अर्करश्मिप्रतीकाशैः like the rays of the Sun, घोरैः by dreadful, दीप्तवदनैः with tips blazing, तूणीगतैः stored in quivers, शरैः with arrows, शोभिताम् adorned with, महारजतवासोभ्याम् scabbards made of silver, असिभ्याम् with a pair of swords, विराजिताम् was shining, रुक्मबिन्दुविचित्राभ्याम् of different colours with golden spots, चर्मभ्याम् with shields, ताम् all of them, काञ्चनभूषितैः decorated with gold, चित्रैः different kinds, आसक्तै: hung, गोधाङ्गुलित्रैः fingerguards made of skin of iguana, मृगैः with the deer, सिंहगुहामिव like the cave of a lion, अरिसङ्घै: with hordes of enemies, अनाधृष्याम् impregnable, पर्णशालाम् hut made of leave, तस्मिन् वने in that forest, ददर्श saw.",
      "explanation": "Lamenting in this way Bharata beheld in that forest an excellent, sacred and enchanting hut covered with a lot of leaves of sala, palmyra and aswakarna trees like a sacrificial altar spread with soft kusa grass. Goldplated bows that resembled the thunderbolt of Indra, powerful and capable of achieving great targets and oppressing the enemies, adorned the hut. Arrows glittering like the rays of the Sun, were dreadful, with blazing heads and stored in quivers adorned it like the hooded serpents illumining the city of Bhogavati (in the nether world). A pair of swords in scabbards made of excellent silver, two shields of different colours with golden spots, fingerguards made of skin of iguana decorated with gold were hanging there. It was impregnable to enemy hordes like the cave of a lion to the deer.",
      "telugu_translation": "ఈ విధంగా విలపిస్తూ భరతుడు ఆ అడవిలో మెత్తని కుశ గడ్డితో వ్యాపించిన యజ్ఞ పీఠం వంటి సాల, తాళపత్ర, అశ్వకర్ణ వృక్షాలతో కప్పబడిన అద్భుతమైన, పవిత్రమైన, మంత్రముగ్ధమైన గుడిసెను చూశాడు. ఇంద్రుని పిడుగును పోలిన బంగారు పూత పూసిన విల్లులు, శక్తివంతమైనవి మరియు గొప్ప లక్ష్యాలను సాధించగల మరియు శత్రువులను అణచివేయగల సామర్థ్యం గలవి, గుడిసెను అలంకరించాయి. సూర్యుని కిరణాల వలె మెరుస్తున్న బాణాలు భయంకరమైనవి, మండుతున్న తలలతో మరియు వణుకులలో భద్రపరచబడి, భోగవతి నగరాన్ని (నెదర్ ప్రపంచంలో) ప్రకాశింపజేసే హుడ్డ్ సర్పాల వలె దానిని అలంకరించాయి. అద్భుతమైన వెండితో చేసిన స్కబార్డ్స్‌లో ఒక జత కత్తులు, బంగారు మచ్చలు కలిగిన వివిధ రంగుల రెండు కవచాలు, బంగారంతో అలంకరించబడిన ఇగువానా చర్మంతో చేసిన ఫింగర్‌గార్డ్‌లు అక్కడ వేలాడుతున్నాయి. అది జింకలకు సింహం గుహలా శత్రు సమూహాలకు అభేద్యమైనది.",
      "comments": ""
    },
    {
      "shloka": 23,
      "shloka_text": "एवं संविलपं स्तस्मिन्वने दशरथात्मजः। ददर्श महातीं पुण्यां पर्णशालां मनोरमाम्।।2.99.18।। सालतालाश्वकर्णानां पर्णैर्बहुभिरावृताम्। विशालां मृदुभिस्तीर्णां कुशैर्वेदिमिवाध्वरे।।2.99.19।। शक्रायुधनिकाशैश्च कार्मुकैर्भारसाधनैः। रुक्मपृष्ठैर्महासारै श्शोभितां शत्रुबाधकैः।।2.99.20।। अर्क रश्मि प्रतीकाशैर्घोरैस्तूणीगतैश्शरैः। शोभितां दीप्तवदनै स्सर्पैर्भोगवतीमिव।।2.99.21।। महारजतवासोभ्यामसिभ्यां च विराजिताम्। रुक्मबिन्दुविचित्राभ्यां चर्मभ्यां चापि शोभिताम्।।2.99.22।। गोधाङ्गुळित्रैरासक्तैश्चित्रैः काञ्चनभूषितैः। अरिसंघैरनाधृष्यां मृगै स्सिंहगुहा मिव।।2.99.23।।",
      "transliteration": "",
      "translation": "एवम् in that way, संविलपन् lamenting, दशरथात्मजः son of Dasaratha (Bharata), तस्मिन् वने in that forest, महतीम् great, पुण्याम् sacred, मनोरमाम् enchanting, सालतालाश्वकर्णानाम् of sala, palmyra and aswakarna trees, बहुभिः by abundance of, मृदुभिः by soft, पर्णैः with leaves, आवृताम् covered, अध्वरे in the sacrifice, कुशैः with kusa grass, तीर्णाम् spread over, विशालाम् spacious, वेदिमिव like altar, शक्रायुधनिकाशैः resembling the thunderbolt of Indra, भारसाधनैः capable of achieving targets, रुक्मपृष्ठैः goldplated, महासारै: by powerful, शत्रुबाधकैः oppressing the enemies, कार्मुकैः with bows, शोभिताम् glittering, सर्पैः with serpents, भोगवतीम् इव like Bhogavati, अर्करश्मिप्रतीकाशैः like the rays of the Sun, घोरैः by dreadful, दीप्तवदनैः with tips blazing, तूणीगतैः stored in quivers, शरैः with arrows, शोभिताम् adorned with, महारजतवासोभ्याम् scabbards made of silver, असिभ्याम् with a pair of swords, विराजिताम् was shining, रुक्मबिन्दुविचित्राभ्याम् of different colours with golden spots, चर्मभ्याम् with shields, ताम् all of them, काञ्चनभूषितैः decorated with gold, चित्रैः different kinds, आसक्तै: hung, गोधाङ्गुलित्रैः fingerguards made of skin of iguana, मृगैः with the deer, सिंहगुहामिव like the cave of a lion, अरिसङ्घै: with hordes of enemies, अनाधृष्याम् impregnable, पर्णशालाम् hut made of leave, तस्मिन् वने in that forest, ददर्श saw.",
      "explanation": "Lamenting in this way Bharata beheld in that forest an excellent, sacred and enchanting hut covered with a lot of leaves of sala, palmyra and aswakarna trees like a sacrificial altar spread with soft kusa grass. Goldplated bows that resembled the thunderbolt of Indra, powerful and capable of achieving great targets and oppressing the enemies, adorned the hut. Arrows glittering like the rays of the Sun, were dreadful, with blazing heads and stored in quivers adorned it like the hooded serpents illumining the city of Bhogavati (in the nether world). A pair of swords in scabbards made of excellent silver, two shields of different colours with golden spots, fingerguards made of skin of iguana decorated with gold were hanging there. It was impregnable to enemy hordes like the cave of a lion to the deer.",
      "telugu_translation": "ఈ విధంగా విలపిస్తూ భరతుడు ఆ అడవిలో మెత్తని కుశ గడ్డితో వ్యాపించిన యజ్ఞ పీఠం వంటి సాల, తాళపత్ర, అశ్వకర్ణ వృక్షాలతో కప్పబడిన అద్భుతమైన, పవిత్రమైన, మంత్రముగ్ధమైన గుడిసెను చూశాడు. ఇంద్రుని పిడుగును పోలిన బంగారు పూత పూసిన విల్లులు, శక్తివంతమైనవి మరియు గొప్ప లక్ష్యాలను సాధించగల మరియు శత్రువులను అణచివేయగల సామర్థ్యం గలవి, గుడిసెను అలంకరించాయి. సూర్యుని కిరణాల వలె మెరుస్తున్న బాణాలు భయంకరమైనవి, మండుతున్న తలలతో మరియు వణుకులలో భద్రపరచబడి, భోగవతి నగరాన్ని (నెదర్ ప్రపంచంలో) ప్రకాశింపజేసే హుడ్డ్ సర్పాల వలె దానిని అలంకరించాయి. అద్భుతమైన వెండితో చేసిన స్కబార్డ్స్‌లో ఒక జత కత్తులు, బంగారు మచ్చలు కలిగిన వివిధ రంగుల రెండు కవచాలు, బంగారంతో అలంకరించబడిన ఇగువానా చర్మంతో చేసిన ఫింగర్‌గార్డ్‌లు అక్కడ వేలాడుతున్నాయి. అది జింకలకు సింహం గుహలా శత్రు సమూహాలకు అభేద్యమైనది.",
      "comments": ""
    },
    {
      "shloka": 24,
      "shloka_text": "प्रागुदक्प्रवणां वेदिं विशालां दीप्तपावकाम्। ददर्श भरतस्तत्र पुण्यां रामनिवेशने।।2.99.24।।",
      "transliteration": "",
      "translation": "भरतः Bharata, तत्र there, रामनिवेशने at Rama's residence, प्रागुदक्प्रवणाम् sloping to the northeast, विशालाम् spacious, दीप्तपावकाम् having flaming fire, पुण्याम् sacred, वेदिम् altar, ददर्श beheld.",
      "explanation": "Bharata beheld at Rama's residence a sacred and spacious altar sloping to the northeast, with a burning fire upon it.",
      "telugu_translation": "భరతుడు రాముని నివాసంలో ఈశాన్యంలో ఒక పవిత్రమైన మరియు విశాలమైన బలిపీఠం, దానిపై మండుతున్న అగ్నిని చూశాడు.",
      "comments": ""
    },
    {
      "shloka": 25,
      "shloka_text": "निरीक्ष्य स मुहूर्तं तु ददर्श भरतो गुरुम्। उटजे राममासीनं जटामण्डलधारिणम्।।2.99.25।।",
      "transliteration": "",
      "translation": "सः भरतः that Bharata, मुहूर्तम् for a moment, निरीक्ष्य looking around, उटजे in the cottage, आसीनम् seated, जटामण्डलधारिणम् wearing matted locks of hair, गुरुम् esteemed brother, रामम् Rama, ददर्श saw.",
      "explanation": "Bharata looked around for a moment and saw his esteemed brother Rama seated in that thatched cottage wearing matted locks of hair.",
      "telugu_translation": "భరతుడు ఒక్క క్షణం చుట్టూ చూసాడు మరియు అతని సోదరుడు రాముడు ఆ గడ్డితో కూడిన కుటీరంలో వెంట్రుకలతో తాళాలు వేసుకుని కూర్చున్నాడు.",
      "comments": ""
    },
    {
      "shloka": 26,
      "shloka_text": "तं तु कृष्णाजिनधरं चीरवल्कलवाससम्। ददर्श राममासीनमभितः पावकोपमम्।।2.99.26।। सिंहस्कन्धं महाबाहुं पुण्डरीकनिभेक्षणम्। पृथिव्यास्सागरान्तायाः भर्तारं धर्मचारिणम्।।2.99.27।। उपविष्टं महाबाहुं ब्रह्माणमिव शाश्वतम्। स्थण्डिले दर्भसंस्तीर्णे सीतया लक्ष्मणेन च।।2.99.28।।",
      "transliteration": "",
      "translation": "कृष्णाजिनधरम् clad in antelope skin, चीरवल्कलवासम् dressed in garments made of bark, अभितः near him, पावकोपमम् resembling blazing fire, आसीनम् seated, सिंहस्कन्दम् with his  shoulders like that of a lion, महाबाहुम् longarmed, पुण्डरीकनिभेक्षणम् with eyes like white lotus, सागरान्तायाः bounded by the ocean, पृथिव्याः of the earth, भर्तारम् the lord, धर्मचारिणम् follower of righteouness, तं रामम् that Rama, ददर्श saw, महाबाहुम् of longarmed one, शाश्वतम् eternal, ब्रह्माणमिव like the creator Brahma, सीतया with Sita, लक्ष्मणेन along with Lakshmana, दर्भसंस्तीर्णे on the ground strewn with darbha grass, स्थण्डिले on the bare ground, उपविष्टम् seated.",
      "explanation": "He saw Rama, lord of the oceanbound earth, seated like blazing fire, clad in antelope skin and garment of bark, with long arms and shoulders like a lion and eyes like white lotuses. The mightyarmed warrior seemed like Brahma, the creator and the eternal, protector of righteousness. Accompanied by Sita and Lakshmana Rama sat on the bare ground strewn with darbha grass.",
      "telugu_translation": "సింహం వంటి పొడవాటి చేతులు, భుజాలు, తెల్లని తామరపువ్వుల వంటి నేత్రాలతో జింక చర్మాన్ని, బెరడు వస్త్రాన్ని ధరించి, మండుతున్న అగ్నిలాగా కూర్చున్న రాముడిని చూశాడు. శక్తివంతమైన యోధుడు బ్రహ్మ, సృష్టికర్త మరియు శాశ్వతమైన, ధర్మాన్ని రక్షించేవాడు. సీతతో పాటు లక్ష్మణ రాములు దర్భ గడ్డితో నిండిన నేలపై కూర్చున్నారు.",
      "comments": ""
    },
    {
      "shloka": 27,
      "shloka_text": "तं तु कृष्णाजिनधरं चीरवल्कलवाससम्। ददर्श राममासीनमभितः पावकोपमम्।।2.99.26।। सिंहस्कन्धं महाबाहुं पुण्डरीकनिभेक्षणम्। पृथिव्यास्सागरान्तायाः भर्तारं धर्मचारिणम्।।2.99.27।। उपविष्टं महाबाहुं ब्रह्माणमिव शाश्वतम्। स्थण्डिले दर्भसंस्तीर्णे सीतया लक्ष्मणेन च।।2.99.28।।",
      "transliteration": "",
      "translation": "कृष्णाजिनधरम् clad in antelope skin, चीरवल्कलवासम् dressed in garments made of bark, अभितः near him, पावकोपमम् resembling blazing fire, आसीनम् seated, सिंहस्कन्दम् with his  shoulders like that of a lion, महाबाहुम् longarmed, पुण्डरीकनिभेक्षणम् with eyes like white lotus, सागरान्तायाः bounded by the ocean, पृथिव्याः of the earth, भर्तारम् the lord, धर्मचारिणम् follower of righteouness, तं रामम् that Rama, ददर्श saw, महाबाहुम् of longarmed one, शाश्वतम् eternal, ब्रह्माणमिव like the creator Brahma, सीतया with Sita, लक्ष्मणेन along with Lakshmana, दर्भसंस्तीर्णे on the ground strewn with darbha grass, स्थण्डिले on the bare ground, उपविष्टम् seated.",
      "explanation": "He saw Rama, lord of the oceanbound earth, seated like blazing fire, clad in antelope skin and garment of bark, with long arms and shoulders like a lion and eyes like white lotuses. The mightyarmed warrior seemed like Brahma, the creator and the eternal, protector of righteousness. Accompanied by Sita and Lakshmana Rama sat on the bare ground strewn with darbha grass.",
      "telugu_translation": "సింహం వంటి పొడవాటి చేతులు, భుజాలు, తెల్లని తామరపువ్వుల వంటి నేత్రాలతో జింక చర్మాన్ని, బెరడు వస్త్రాన్ని ధరించి, మండుతున్న అగ్నిలాగా కూర్చున్న రాముడిని చూశాడు. శక్తివంతమైన యోధుడు బ్రహ్మ, సృష్టికర్త మరియు శాశ్వతమైన, ధర్మాన్ని రక్షించేవాడు. సీతతో పాటు లక్ష్మణ రాములు దర్భ గడ్డితో నిండిన నేలపై కూర్చున్నారు.",
      "comments": ""
    },
    {
      "shloka": 28,
      "shloka_text": "तं तु कृष्णाजिनधरं चीरवल्कलवाससम्। ददर्श राममासीनमभितः पावकोपमम्।।2.99.26।। सिंहस्कन्धं महाबाहुं पुण्डरीकनिभेक्षणम्। पृथिव्यास्सागरान्तायाः भर्तारं धर्मचारिणम्।।2.99.27।। उपविष्टं महाबाहुं ब्रह्माणमिव शाश्वतम्। स्थण्डिले दर्भसंस्तीर्णे सीतया लक्ष्मणेन च।।2.99.28।।",
      "transliteration": "",
      "translation": "कृष्णाजिनधरम् clad in antelope skin, चीरवल्कलवासम् dressed in garments made of bark, अभितः near him, पावकोपमम् resembling blazing fire, आसीनम् seated, सिंहस्कन्दम् with his  shoulders like that of a lion, महाबाहुम् longarmed, पुण्डरीकनिभेक्षणम् with eyes like white lotus, सागरान्तायाः bounded by the ocean, पृथिव्याः of the earth, भर्तारम् the lord, धर्मचारिणम् follower of righteouness, तं रामम् that Rama, ददर्श saw, महाबाहुम् of longarmed one, शाश्वतम् eternal, ब्रह्माणमिव like the creator Brahma, सीतया with Sita, लक्ष्मणेन along with Lakshmana, दर्भसंस्तीर्णे on the ground strewn with darbha grass, स्थण्डिले on the bare ground, उपविष्टम् seated.",
      "explanation": "He saw Rama, lord of the oceanbound earth, seated like blazing fire, clad in antelope skin and garment of bark, with long arms and shoulders like a lion and eyes like white lotuses. The mightyarmed warrior seemed like Brahma, the creator and the eternal, protector of righteousness. Accompanied by Sita and Lakshmana Rama sat on the bare ground strewn with darbha grass.",
      "telugu_translation": "సింహం వంటి పొడవాటి చేతులు, భుజాలు, తెల్లని తామరపువ్వుల వంటి నేత్రాలతో జింక చర్మాన్ని, బెరడు వస్త్రాన్ని ధరించి, మండుతున్న అగ్నిలాగా కూర్చున్న రాముడిని చూశాడు. శక్తివంతమైన యోధుడు బ్రహ్మ, సృష్టికర్త మరియు శాశ్వతమైన, ధర్మాన్ని రక్షించేవాడు. సీతతో పాటు లక్ష్మణ రాములు దర్భ గడ్డితో నిండిన నేలపై కూర్చున్నారు.",
      "comments": ""
    },
    {
      "shloka": 29,
      "shloka_text": "तं दृष्ट्वा भरत श्श्रीमान् दुःखशोकपरिप्लुतः। अभ्यधावत धर्मात्मा भरतः कैकेयी सुतः।।2.99.29।।",
      "transliteration": "",
      "translation": "श्रीमान् majestic, भरतः Bharata, तम् that Rama, दृष्ट्वा having seen, दुःखशोकपरिप्लुतः overwhelmed with grief and distress, धर्मात्मा righteous, कैकयीसुतः son of Kaikeyi, भरतः Bharata, अभ्यधावत ran towards him.",
      "explanation": "Beholding Rama, Bharata the majestic and righteous son of Kaikeyi overwhelmed with grief and distress rushed towards him.",
      "telugu_translation": "రాముడిని చూసి, కైకేయి యొక్క గంభీరమైన మరియు నీతిమంతుడైన భరతుడు దుఃఖం మరియు బాధతో అతని వైపు దూసుకుపోయాడు.",
      "comments": ""
    },
    {
      "shloka": 30,
      "shloka_text": "दृष्ट्वैव विललापाऽर्तो बाष्पसन्दिग्धया गिरा। अशक्नुवन् धारयितुं धैर्याद्वचनमब्रवीत्।।2.99.30।।",
      "transliteration": "",
      "translation": "दृष्ट्वैव as soon as he saw, आर्तः anguished, बाष्पसन्दिग्धया choked with tears, गिरा with words, विललाप lamented, धैर्यात् with courage, धारयितुम् to restrain, अशक्नुवन् being unable, वचनम् these words, अब्रवीत् said.",
      "explanation": "On seeing Rama, Bharata could not control his grief with patience and lamented in great anguish and with words choked with tears said:",
      "telugu_translation": "రాముని చూడగానే భరతుడు తన దుఃఖాన్ని సహనంతో అదుపు చేసుకోలేక తీవ్ర వేదనతో విలపిస్తూ కన్నీళ్లతో ఉక్కిరిబిక్కిరి అయ్యాడు.",
      "comments": ""
    },
    {
      "shloka": 31,
      "shloka_text": "य स्संसदि प्रकृतिभिर्भवेद्युक्त उपासितुम्। वन्यैर्मृगैरुपासीन स्सोऽयमास्ते ममाग्रजः।।2.99.31।।",
      "transliteration": "",
      "translation": "यः he who, संसदि in the royal assembly, प्रकृतिभिः by ministers and other subjects, उपासितुम् to be attended upon, युक्तः one who deserves, भवेत् becomes, सः he, अयम् this, man, मम my, अग्रजः elder brother, वन्यैः wild, मृगैः by the beasts, उपासीनः आस्ते is being attended.",
      "explanation": "My elder brother who deserves to be attended by ministers and other subjects in the royal assembly sits here today in the forest surrounded by wild beasts.",
      "telugu_translation": "రాజసభలో మంత్రులతో పాటు ఇతర సబ్జెక్టులకు హాజరయ్యే నా అన్నయ్య ఈరోజు ఇక్కడ క్రూరమృగాల చుట్టూ ఉన్న అడవిలో కూర్చున్నాడు.",
      "comments": ""
    },
    {
      "shloka": 32,
      "shloka_text": "वासोभिर्बहुसाहस्रैर्यो महात्मा पुरोचितः। मृगाजिने सोऽयमिह प्रवस्ते धर्ममाचरन्।।2.99.32।।",
      "transliteration": "",
      "translation": "यः महात्मा that magnanimous (Rama), पुरा formerly, बहुसाहस्रैः with many thousands, वासोभिः with clothes, उचितः was accustomed, सः such, अयम् now, धर्मम् righteousness, आचरन् practising, मृगाजिने two deer kins, प्रवस्ते is wearing.",
      "explanation": "Such magnanimous Rama, a follower of dharma, accustomed to be attired in  thousands of dresses in the past now clad in two deer skins, is practising righteousness.",
      "telugu_translation": "అటువంటి మహానుభావుడైన రాముడు, ధర్మాన్ని అనుసరించేవాడు, గతంలో వేలకొలది వేషధారణలకు అలవాటు పడ్డాడు, ఇప్పుడు రెండు జింక చర్మాలు ధరించి, ధర్మాన్ని ఆచరిస్తున్నాడు.",
      "comments": ""
    },
    {
      "shloka": 33,
      "shloka_text": "अधारयद्यो विविधाश्चित्रास्सुमनसस्तदा। सोऽयं जटाभारमिमं वहते राघवः कथम्।।2.99.33।।",
      "transliteration": "",
      "translation": "यः that Rama, तदा then, विविधाः various, चित्राः colours, सुमनसः flowers, आधारयत् wore, सः such a man, अयं राघवः this Rama, इमं जटाभारम् the weight of matted hair, कथम् how, वहते is able to bear?",
      "explanation": "How is it that Rama who used to wear variegated flowers formerly, now bears these heavy matted locks?",
      "telugu_translation": "ఇంతకుముందు రంగురంగుల పువ్వులు ధరించే రాముడు ఇప్పుడు ఈ బరువైన తాళాలు ఎలా భరించాడు?",
      "comments": ""
    },
    {
      "shloka": 34,
      "shloka_text": "यस्य यज्ञैर्यथादिष्टैर्युक्तो धर्मस्य सञ्चयः। शरीरक्लेशसम्भूतं स धर्मं परिमार्गते।।2.99.34।।",
      "transliteration": "",
      "translation": "यथोद्विष्टैः in accordance with desire, यज्ञैः with sacrifices, यस्य to whom, धर्मस्य righteousness, सञ्चयः accumulation, युक्तः was quite possible, सः such Rama, शरीरक्लेशसंभूतम् rising due to mortification of body, धर्मम् righteouness, परिमार्गते is seeking.",
      "explanation": "That Rama, who in accordance with tradition deserves accredition of religious merit through sacrifices now seeks it through mortification of body.",
      "telugu_translation": "ఆ రాముడు, సాంప్రదాయం ప్రకారం, త్యాగాల ద్వారా మతపరమైన యోగ్యతను పొందటానికి అర్హుడు, ఇప్పుడు శరీర మృత్యువు ద్వారా దానిని కోరుతున్నాడు.",
      "comments": ""
    },
    {
      "shloka": 35,
      "shloka_text": "चन्दनेन महार्हेण यस्याङ्गमुपसेवितम्। मलेन तस्याङ्गमिदं कथमार्यस्य सेव्यते।।2.99.35।।",
      "transliteration": "",
      "translation": "यस्य whose, अङ्गम् body, महार्हेण by highly valuable, चन्दनेन with sandal paste, उपसेवितम्  smeared, तस्य his, आर्यस्य esteemed brother's, इदम् अङ्गम् this body, मलेन with dirt, कथम् how, सेव्यते is being served?",
      "explanation": "How is it that the body of my venerable brother which was once smeared with expensive, fragrant sandal paste is now covered with dust?",
      "telugu_translation": "ఒకప్పుడు ఖరీదైన, సువాసనతో కూడిన గంధం పూసుకున్న నా సోదరుడి శరీరం ఇప్పుడు దుమ్ముతో ఎలా కప్పబడి ఉంది?",
      "comments": ""
    },
    {
      "shloka": 36,
      "shloka_text": "मन्निमित्तमिदं दुःखं प्राप्तो रामः सुखोचितः। धिग्जीवितं नृशंसस्य मम लोकविगर्हितम्।।2.99.36।।",
      "transliteration": "",
      "translation": "सुखोचितः accustomed to comforts, रामः Rama, मन्निमित्तम् on my account, इदं दुःखम् this misfortune, प्राप्तः has obtained, नृशंसस्य of a cruel one, मम my, लोकविगर्हितम् condemned by the world, जीवितम् धिक् fie on my life.",
      "explanation": "It is on my account that Rama who was accustomed to all comforts has fallen into this misfortune. Fie on my life of cruelty which is condemned by the world.",
      "telugu_translation": "సకల సుఖాలకు అలవాటు పడిన రాముడు ఈ దుస్థితిలో పడ్డాడని నా ఖాతాలో పడింది. ప్రపంచం ఖండించిన క్రూరత్వంతో కూడిన నా జీవితానికి దండన.",
      "comments": ""
    },
    {
      "shloka": 37,
      "shloka_text": "इत्येवं विलपन्दीनः प्रस्विन्नमुखपङ्कजः। पादावप्राप्य रामस्य पपात भरतो रुदन्।।2.99.37।।",
      "transliteration": "",
      "translation": "भरतः Bharata, दीनः miserable, प्रस्विन्नमुखपङ्कजः lotuslike countenance full of sweat, इत्येवम् thus, विलपन् lamenting, रामस्य Rama's, पादौ feet, अप्राप्य before reaching, रुदन् crying in distress, पपात fell down.",
      "explanation": "Thus Bharata lamented in misery and with his lotuslike countenanace sweating  before reaching Rama's feet fell down, crying in distress.",
      "telugu_translation": "ఆ విధంగా భరతుడు దుఃఖంతో విలపించాడు మరియు రాముని పాదాలను చేరుకోకముందే తన కమలంలాంటి ముఖంతో చెమటలు పట్టి, బాధతో ఏడ్చాడు.",
      "comments": ""
    },
    {
      "shloka": 38,
      "shloka_text": "दुःखाभितप्तो भरतो राजपुत्रो महाबलः। उक्त्वाऽर्येति सकृद्दीनं पुनर्नोवाच किञ्चन।।2.99.38।।",
      "transliteration": "",
      "translation": "महाबलः mighty, राजपुत्रः prince, भरतः Bharata, दुःखाभितप्तः oppressed with grief, आर्य इति saying o Arya (venerable one), सकृत् once, दीनम् in distress, उक्त्वा having said, पुनः again, किञ्चन anything, नोवाच could not speak.",
      "explanation": "Mighty prince Bharata, oppressed with grief, could only say, O Arya (venerable one) And in distress could not speak any more.",
      "telugu_translation": "శోకంతో అణచివేయబడిన పరాక్రమవంతుడైన భరత యువరాజు, ఓ ఆర్య (పూజనీయుడు) అని మాత్రమే చెప్పగలిగాడు మరియు బాధలో ఇక మాట్లాడలేకపోయాడు.",
      "comments": ""
    },
    {
      "shloka": 39,
      "shloka_text": "बाष्पाभिहतकण्ठश्च प्रेक्ष्य रामं यशस्विनम्। आर्येत्येवाभिसङ्क्रुश्य व्याहर्तुं नाशकत्तदा।।2.99.39।।",
      "transliteration": "",
      "translation": "यशस्विनम् glorious, रामम् Rama, प्रेक्ष्य on seeing, बाष्पाभिहतकण्ठश्च with choked throat, अथ then, आर्येत्येव O Arya, सङ्क्रुश्य crying out, तदा thereafter, व्याहर्तुम् to talk further, नाशकत् was not able.",
      "explanation": "As he beheld the glorious Rama, with his throat choken with tears, he cried out, O Arya (venerable one) and thereafter, was unable to speak any more.",
      "telugu_translation": "కన్నీళ్లతో ఉక్కిరిబిక్కిరైన తన కంఠంతో మహిమాన్వితమైన రాముడిని చూడగానే, అతను ఆర్యా (పూజనీయుడు) అని అరిచాడు మరియు ఆ తర్వాత మాట్లాడలేకపోయాడు.",
      "comments": ""
    },
    {
      "shloka": 40,
      "shloka_text": "शत्रुघ्नश्चापि रामस्य ववन्दे चरणौ रुदन्। तावुभौ स समालिङ्ग्य रामश्चाश्रूण्यवर्तयत्।।2.99.40।।",
      "transliteration": "",
      "translation": "शत्रुघ्नश्चापि Satrughna too, रुदन् weeping, रामस्य Rama's, चरणौ feet, ववन्दे prostrated, सः रामश्च that Rama also, तौ उभौ the two of them, समालिङ्ग्य having embraced, अश्रूणि  tears, अवर्तयत् shed.",
      "explanation": "Satrughna also prostrated himself at the feet of tearful Rama who embraced both of them.",
      "telugu_translation": "శతృఘ్నుడు కూడా వారిద్దరినీ ఆలింగనం చేసుకున్న కన్నీటి రాముడి పాదాలకు సాష్టాంగపడ్డాడు.",
      "comments": ""
    },
    {
      "shloka": 41,
      "shloka_text": "ततस्सुमन्त्रेण गुहेन चैव समीयतु राजसुतावरण्ये। दिवाकरश्चैव निशाकरश्च यथाऽम्बरे शुक्रबृहस्पतिभ्याम्।।2.99.41।।",
      "transliteration": "",
      "translation": "ततः therafter, अरण्ये in the forest, राजसुतौ the princes (Rama and Lakshmana), अम्बरे in the sky, दिवाकरश्चैव Sun, निशाकरश्च Moon, शुक्रबृहस्पतिभ्याम् with Sukra and Brihaspathi, यथा similarly, सुमन्त्रेण with Sumantra, गुहेन चैव with Guha, समीयतुः met.",
      "explanation": "Thereafter, princes Rama and Lakshmana joined Sumantra and Guha in the forest like the Sun and the Moon meeting the planets Sukra and Brihaspati in the sky.",
      "telugu_translation": "ఆ తర్వాత, రాకుమారులు రాముడు మరియు లక్ష్మణుడు సూర్యుడు మరియు చంద్రుడు ఆకాశంలో శుక్ర మరియు బృహస్పతి గ్రహాలను కలుసుకున్నట్లుగా అడవిలో సుమంత్ర మరియు గుహతో చేరారు.",
      "comments": ""
    },
    {
      "shloka": 42,
      "shloka_text": "तान्पार्थिवान्वारणयूथपाभान्समागतां स्तत्र महत्यरण्ये। वनौकसस्तेऽपि समीक्ष्य सर्वेऽप्यश्रूण्यमुञ्चन्प्रविहाय हर्षम्।।2.99.42।।",
      "transliteration": "",
      "translation": "ते सर्वे they all, वनौकसः inhabitants of the forest, तत्र there, महति in great, अरण्ये in the forest, समागतान् united, वारणयूथपाभान् with the effulgence of mighty leaders of elephant herds, तान् पार्थिवान् those kings, समीक्ष्य on seeing, हर्षम् delight, प्रविहाय having forsaken, अश्रूणि tears, अमुञ्चन् shed.",
      "explanation": "On seeing the princes now assembled in the great forest like mighty leaders of elephant herds, inhabitants of the forest had nothing but tears of grief, not joy, to shed. इत्यार्षे श्रीमद्रामायणे वाल्मीकीय आदिकाव्ये अयोध्याकाण्डे एकोनशततमस्सर्गः।। Thus ends the ninetyninth sarga in Ayodhyakanda of the holy Ramayana, the first epic composed by sage Valmiki.",
      "telugu_translation": "ఏనుగుల గుంపుల పరాక్రమ నాయకుల్లాగా ఇప్పుడు మహా అరణ్యంలో సమావేశమైన యువరాజులను చూసిన అరణ్యవాసులకు కన్నీళ్లు తప్ప మరేమీ లేవు, సంతోషం కాదు. ఇత్యార్షే శ్రీమద్రామాయణే వాల్మీకీయ ఆదికావ్యే అయోధ్యాకాణ్డే ఏకోనశతమ్. వాల్మీకి మహర్షి రచించిన మొదటి ఇతిహాసం పవిత్ర రామాయణంలోని తొంభైతొమ్మిదవ సర్గ అయోధ్యకాండలో ఈ విధంగా ముగుస్తుంది.",
      "comments": ""
    }
  ]
}